<?xml version="1.0" encoding="utf-8"?><ObjectCollector>
	<Configuration ConfigName="Outlook Configuration" ChangeDescription="1.0.1411.20" ConfigVersion="1.0.1411.20" ArticleURL="http://go.microsoft.com/fwlink/p/?LinkID={2}" DownloadURL="http://www.microsoft.com/office/offcat" FixItURL="http://go.microsoft.com/?linkid={0}" ReferencedFiles="common.config.xml,officeupdates.config.xml" Symptoms="1">
		<Substitution Name="APPNAME">Outlook</Substitution>
    <Substitution Name="DAYS"></Substitution>
    <Substitution Name="MAXEVENTS"></Substitution>
		<DataPostprocessor Name="0 Configuration Sumary Data Generation" Assembly="BPA.OfficeCommon.dll" Class="Microsoft.WindowsServerSystem.BestPracticesAnalyzer.Common.ConfigSummaryDataPostprocessor"/>
		<ConfigPreprocessor Name="0 OutlookGlobalSubstitutionConfigPreprocessor Preprocessor" Assembly="BPA.Common.dll" Class="Microsoft.WindowsServerSystem.BestPracticesAnalyzer.Common.OutlookGlobalSubstitutionConfigPreprocessor"/>
		<ConfigPreprocessor Name="1 Type Preprocessor" Assembly="BPA.Common.dll" Class="Microsoft.WindowsServerSystem.BestPracticesAnalyzer.Common.TypeConfigPreprocessor"/>
		<ObjectProcessor Name="Group" Assembly="BPA.Common.dll" Class="Microsoft.WindowsServerSystem.BestPracticesAnalyzer.Common.GroupObjectProcessor"/>
		<ObjectProcessor Name="If" Assembly="BPA.Common.dll" Class="Microsoft.WindowsServerSystem.BestPracticesAnalyzer.Common.IfObjectProcessor"/>
		<ObjectProcessor Name="EventLog" Assembly="BPA.ConfigCollector.dll" Class="Microsoft.WindowsServerSystem.BestPracticesAnalyzer.Extensions.EvLog"/>
		<ObjectProcessor Name="MSI" Assembly="BPA.ConfigCollector.dll" Class="Microsoft.WindowsServerSystem.BestPracticesAnalyzer.Extensions.MSI"/>
		<ObjectProcessor Name="Outlook" Assembly="BPA.OutlookCollector.dll" Class="Microsoft.WindowsServerSystem.BestPracticesAnalyzer.Extensions.OutlookObjectProcessor"/>
		<ObjectProcessor Name="Engine" Assembly="BPA.Common.dll" Class="Microsoft.WindowsServerSystem.BestPracticesAnalyzer.Common.EngineObjectProcessor"/>
		<ObjectProcessor Name="File" Assembly="BPA.ConfigCollector.dll" Class="Microsoft.WindowsServerSystem.BestPracticesAnalyzer.Extensions.FileObjectProcessor"/>
		<ObjectProcessor Name="Registry" Assembly="BPA.ConfigCollector.dll" Class="Microsoft.WindowsServerSystem.BestPracticesAnalyzer.Extensions.RegistryObjectProcessor"/>
		<ExtFormat Name="Wow6432Node" Assembly="BPA.OfficeCommon.dll" Class="Microsoft.WindowsServerSystem.BestPracticesAnalyzer.Formats" Convert="Wow6432Node"></ExtFormat>
		<RestrictionType Name="Task">
			<Option Name="Offline Scan" Text="RestrictionText" Title="RestrictionTitle" Filter="True"/>
		</RestrictionType>
	</Configuration>

	<Object Type="MSI" Key1="INSTALLEDAPPLICATIONS" Key5="Outlook" Key6="outlook" Key7="%MAJORVERSION%" Display="Hide">
		<Setting Key1="Bitness" Substitution="WOW6432NODE" SubstitutionFormat="Wow6432Node" Display="Hide">
		</Setting>
		<Setting Key1="Bitness" Substitution="APPBITNESS" Display="Hide">
      <Rule Name="bitness" Query="$."></Rule>
		</Setting>
    <Setting Key1="FullVersion" Display="Hide">
		  <Rule Name="n2DigitVersion" Query="number(substring($.,1,2))"></Rule>
			<Rule Name="sFullAppVersion" Query="$."></Rule>
		</Setting>
	  <Setting Key1="Name" Display="Hide">
			<Rule Name="appName" Query="$.">
			</Rule>
		</Setting>
		<Setting Key1="Version" Substitution="APPVERSION" Display="Hide">
			<Rule Name="n4DigitSKUVersion" Query="$."></Rule>
		</Setting>
		<Setting Key1="Type" Substitution="INSTALLTYPE" Display="Hide">
			<Rule Name="nInstallType" Query="$."></Rule>
      <Rule Name="f2013MSI" Query="$n4DigitSKUVersion='2013' and $.='MSI'"></Rule>
		</Setting>
	</Object>
  <Object Type="Registry" Key2="HKEY_LOCAL_MACHINE" Key3="Software\Microsoft\Office\Outlook\Addins" Key5="Subtree" Display="Hide">
    <Setting Key1="__KEYPATH" Substitution="KP" Display="Hide"></Setting>
		  <Rule Name="fEvernote" Query="../Instance/Setting[@Key1='__KEYPATH' and contains(Value,'EvernoteOL.Connect')]"></Rule>
  </Object>
  <Object Type="Registry" Key2="HKEY_LOCAL_MACHINE" Key3="Software\Wow6432Node\Microsoft\Office\Outlook\Addins" Key5="Subtree" Display="Hide">
    <Setting Key1="__KEYPATH" Substitution="KP" Display="Hide"></Setting>
	    <Rule Name="fEvernoteWow" Query="../Instance/Setting[@Key1='__KEYPATH' and contains(Value,'EvernoteOL.Connect')]"></Rule>
  </Object>
  <Object Type="If" Key1="'%MAJORAPPVERSION%'='15.0' and '%INSTALLTYPE%'='MSI' and '%APPBITNESS%'='x86'">
    <Object Type="MSI" Key1="MSIENUMCLIENTS" Key2="{E9E5CFFC-AFFE-4F83-A695-7734FA4775B9}">
  	  <Setting Key1="ProductCode" Substitution="PRODUCTCODE" Display="Hide"></Setting>
		  <Setting Key1="ProductCode" Substitution="REGPRODUCTCODE" SubstitutionFormat="({)(.*)(})----$2" Display="Hide"></Setting>
		  <Object Type="If" Key1="contains('%PRODUCTCODE%','0FF1CE')">
			  <Rule Name="SKU2013" Query="substring('%PRODUCTCODE%',11,4)"></Rule>
			  <Rule Name="ReleaseType2013" Query="substring('%PRODUCTCODE%',3,1)"></Rule>
			  <Object Type="Group" Name="ProductCode =%PRODUCTCODE%" Display="Hide">
				  <Setting Key1="" Display="Hide"></Setting>
			  </Object>
			  <Object Type="MSI" Key1="MSIGETPRODUCTINFO" Key2="%PRODUCTCODE%">
				  <Object Type="Registry" Key2="HKEY_LOCAL_MACHINE" Key3="Software\%WOW6432NODE%\Microsoft\Office\15.0\Common\InstalledPackages\%REGPRODUCTCODE%" Display="Hide">
					  <Setting Key1="ProductVersion" Display="Hide">
						  <Rule Name="fOfficeProductVersion15" Query="$." AlwaysEvaluate="True"></Rule>
					  </Setting>
				  </Object>
				  <Setting Key1="ProductName" Display="Hide">
					  <Rule Name="SKUName2013" Query="$."></Rule>
				  </Setting>
			  </Object>
		  </Object>
	  </Object>
  </Object>
	<Object Type="If" Key1="'%MAJORAPPVERSION%'='15.0' and '%INSTALLTYPE%'='MSI' and '%APPBITNESS%'='x64'">
		<Object Type="MSI" Key1="MSIENUMCLIENTS" Key2="{3A5F96E7-F51D-4942-98DB-3CD037FB39E5}">
			<Setting Key1="ProductCode" Substitution="PRODUCTCODE" Display="Hide"></Setting>
			<Setting Key1="ProductCode" Substitution="REGPRODUCTCODE" SubstitutionFormat="({)(.*)(})----$2" Display="Hide"></Setting>
			<Object Type="If" Key1="contains('%PRODUCTCODE%','0FF1CE')">
				<Rule Name="SKU201364" Query="substring('%PRODUCTCODE%',11,4)"></Rule>
				<Rule Name="ReleaseType201364" Query="substring('%PRODUCTCODE%',3,1)"></Rule>
				<Object Type="Group" Name="ProductCode =%PRODUCTCODE%" Display="Hide">
					<Setting Key1="" Display="Hide"></Setting>
				</Object>
				<Object Type="MSI" Key1="MSIGETPRODUCTINFO" Key2="%PRODUCTCODE%">
					<Object Type="Registry" Key2="HKEY_LOCAL_MACHINE" Key3="Software\%WOW6432NODE%\Microsoft\Office\15.0\Common\InstalledPackages\%REGPRODUCTCODE%" Display="Hide">
						<Setting Key1="ProductVersion" Display="Hide">
							<Rule Name="fOfficeProductVersion15x64" Query="$." AlwaysEvaluate="True"></Rule>
						</Setting>
					</Object>
					<Setting Key1="ProductName" Display="Hide">
						<Rule Name="SKUName201364" Query="$."></Rule>
					</Setting>
				</Object>
			</Object>
		</Object>
	</Object>

  <Type Name="OutlookCrashes">

	  <!--EVENT LOGS-->
	  <Object Type="EventLog" Key1="Application" Key3="1000" Key4="outlook.exe" Key5="%MAXEVENTS%" Key7="%DAYS%" Key8="10000" Task="Offline Scan">
	  	<Rule Name="nCrashCount" Query="count(../Instance)"></Rule>
  		<Setting Key1="__ALL"></Setting>
	  	<Setting Key1="Faulting Application Name" Display="Right"></Setting>
		  <Setting Key1="Faulting Application Version" Display="Right">
			  <Rule Name="nFaultingAppVersion" Query="$."></Rule>
  		</Setting>
	  	<Setting Key1="Faulting Application Timestamp" Display="Right">
		  	<Rule Name="faultAppTimeStamp" Query="$."></Rule>
		  </Setting>
		  <Setting Key1="Faulting Module Name" Display="Right">
			  <Rule Name="faultModuleName" Query="$."></Rule>
			  <Rule Name="sEvernoteCrash" Query="$n2DigitVersion&gt;14 and $fEvernote and starts-with($.,'Evernote')" Error="Warning" Title="Evernote add-in has caused one or more crashes in Outlook" Text="A third-party add-in called Evernote.Outlook is installed and has caused Outlook to crash. Please click the 'Click here to see possible solutions...' link for details on how to disable this add-in." GUID="301344" SSID="027ab56f-3e5c-459b-b6fb-1f91a1a67c3a" Symptoms="Crash,Add-ins,Error message"></Rule>
			  <Rule Name="sEvernoteCrashWow" Query="$n2DigitVersion&gt;14 and $fEvernoteWow and starts-with($.,'Evernote')" Error="Warning" Title="Evernote add-in has caused one or more crashes in Outlook" Text="A third-party add-in called Evernote.Outlook is installed and has caused Outlook to crash. Please click the 'Click here to see possible solutions...' link for details on how to disable this add-in." GUID="301344" SSID="5e36b273-5714-4564-9392-bcf6f078b899" Symptoms="Crash,Add-ins,Error message"></Rule>
			  <Rule Name="sFaultWWLib15045351507" Query="starts-with(lower-case($.),'wwlib') and ($nFaultingModuleVersion='15.0.4535.1507')" Error="Error" Title="Crashing issue with Wwlib.dll 15.0.4535.1507 found" Text="A crashing issue in Outlook.exe that was caused by Wwlib.dll (version 15.0.4535.1507) was found in the application event log. Please click the 'Click here ...' link below for details." GUID="330777" SSID="ae5c5b83-13b2-48ab-8833-5e84300f7a0b" Symptoms="Crash,Add-ins,Error message"/>
			  <Rule Name="sRedemption" P0="$nFaultingModuleVersion" Query="starts-with(lower-case($.),'redemption') and (number(substring($nFaultingModuleVersion,1,1))&lt;5 or (number(substring($nFaultingModuleVersion,1,1))=5 and number(substring($nFaultingModuleVersion,3,1))&lt;2))" Error="Error" Title="Crash caused by redemption.dll" Text="This version of redemption.dll ({0}) has some known issues" GUID="267390" SSID="a8413340-c28f-44e9-a871-367428e24f29" Symptoms="Crash,Add-ins,Error message"></Rule>
			  <Rule Name="sFaultOlmapiKB2837618" Query="starts-with(lower-case($.),'olmapi32') and ($nFaultingModuleVersion='15.0.4551.1003') and $OfficeUpdates_sKB2837618Installed" Error="Error" Title="Crashing issue with Olmapi32.dll 15.0.4551.1003 found" Text="A crashing issue in Outlook.exe that was caused by Olmapi32.dll (version 15.0.4551.1003) was found in the application event log. This occurs when the update from KB2837618 is installed. Please click the 'Click here ...' link below for details." GUID="335869" SSID="345f8f88-06c9-4064-8af9-bd2dca934760" Symptoms="Crash,Add-ins,Error message"></Rule>
			  <Rule Name="sFaultAPLZOD32Crash" Query="$n2DigitVersion=15 and starts-with(lower-case($.),'aplzod32')" Error="Error" Title="Crashing issue caused by APLZOD32.dll found" Text="A crashing issue in Outlook.exe that was caused by third-party dll (APLZOD32.dll) was found in the application event log. Please click the 'Click here ...' link below for details on a resolution." GUID="392651" SSID="0f7a30b9-d5b2-4e4e-8723-e85950b13717" Symptoms="Crash,Add-ins,Error message"></Rule>
		  </Setting>
		  <Setting Key1="Faulting Module Version" Display="Right">
			  <Rule Name="nFaultingModuleVersion" Query="$."></Rule>
		  </Setting>
		  <Setting Key1="Faulting Module Timestamp" Display="Right">
			  <Rule Name="faultModuleTimestamp" Query="$."></Rule>
		  </Setting>
		  <Setting Key1="Exception code" Display="Right"></Setting>
		  <Setting Key1="Fault offset" Display="Right">
			  <Rule Name="faultOffset" Query="$."></Rule>
		  </Setting>
		  <Setting Key1="Faulting Application Path" Display="Right"></Setting>
		  <Setting Key1="Faulting Module Path" Display="Right"></Setting>
		  <Setting Key1="Timegenerated" Display="Hide">
			  <Rule Name="TimeOfCrash" Query="$."/>
		  </Setting>
		  <Setting Key1="Message" Display="Hide">
        <Rule Name="sCrashMessage" Query="$."></Rule>
  		  <Rule Name="crashLookup" Query="true()" Title="Event 1000 ({9})" Text="{8}" Error="Error" Internal="True" P0="if($bitness='x86','Crash32','Crash64')" P1="'outlook.exe'" P2="$nFaultingAppVersion" P3="$faultAppTimeStamp" P4="$faultModuleName" P5="$nFaultingModuleVersion" P6="$faultModuleTimestamp" P7="$faultOffset" P8="$sCrashMessage" P9="$TimeOfCrash" Symptoms="Crash event lookup"></Rule>
		  </Setting>
		  <Setting Key1="FaultingModule" Display="Hide">
			  <Rule Name="sFaultingModule" Query="lower-case($.)"></Rule>
		  </Setting>
		  <Setting Key1="FaultingModuleVersion" Display="Hide">
			  <Rule Name="sFaultingModuleVersion" Query="$."></Rule>
		  </Setting>
		  <Setting Key1="FaultingModulePath" Substitution="FAULTMODPATH" Display="Hide">
			  <Rule Name="sFaultingModulePath" Query="$."></Rule>
		  </Setting>
		  <Object Type="File" Key2="%FAULTMODPATH%" Display="Hide">
			  <Setting Key1="CompanyName" Display="Hide">
				  <Rule Name="sFaultModuleCompanyName" Query="$."></Rule>
				  <Rule Error="Error" Name="sThirdPartyFaultModulenot14" Query="$n2DigitVersion&lt;14 and not($sFaultingModule='umoutlookaddin.dll' or $sFaultingModule='colleagueimport.dll') and not(contains($sFaultModuleCompanyName,'Microsoft'))" P0="$sFaultingModule" P1="$sFaultModuleCompanyName" P2="$TimeOfCrash" Title="Outlook crash due to third-party module: {0} on: {2}" Text="To resolve this issue, make sure Outlook is up-to-date. If the problem continues, update the software/add-in related to this dll file. For reference, the third-party vendor is: {1}." GUID="267388" SSID="ac9f21d7-d7d5-4b5c-92c9-d18f7de203e8" Symptoms="Crash,Error message,Event Log"></Rule>
				  <Rule Error="Error" Name="sThirdPartyFaultModule1415" Query="($n2DigitVersion=14 or $n2DigitVersion=15) and not($sFaultingModule='umoutlookaddin.dll' or $sFaultingModule='colleagueimport.dll') and not(contains($sFaultModuleCompanyName,'Microsoft'))" P0="$sFaultingModule" P1="$sFaultModuleCompanyName" P2="$TimeOfCrash" Title="Outlook crash due to third-party module: {0} on: {2}" Text="To resolve this issue, make sure Outlook is up-to-date. If the problem continues, update the software/add-in related to this dll file. For reference, the third-party vendor is: {1}." GUID="267389" SSID="fa1090d2-da36-43ba-b1a4-4fe0bc038026" Symptoms="Crash,Error message,Event Log"></Rule>
			  </Setting>
		  </Object>
    
      <Rule Name="nFaultMsvcr90Ox00059e89" Query="count(../Instance[Setting[@Key1='Faulting Module Name' and (starts-with(lower-case(Value),'msvcr90.'))] and Setting[@Key1='Fault offset' and (lower-case(Value)='00059e89')]])"></Rule>
      <Rule Name="sFaultMsvcr90Ox00059e89" Query="$n2DigitVersion=14 and $nFaultMsvcr90Ox00059e89&gt;0" Error="Error" P0="$nFaultMsvcr90Ox00059e89" Title="Outlook crashing issue with Msvcr90.dll found" Text="A crashing issue in Outlook.exe that was caused by Msvcr90.dll was found {0} times in the application event log over the last 14 days. This problem has been known to be caused by a corrupt nickname cache.&#xA;&#xA;Please click the 'Click here ...' link below for details." GUID="397389" SSID="9ec51aaa-6003-4390-ab09-222d0812e626" Symptoms="Crash,Error message,Event Log"/>
      <Rule Name="nFaultNRTMsgLibn" Query="count(../Instance/Setting[@Key1='Faulting Module Name' and (starts-with(lower-case(Value),'nrtmsglibn'))])"/>
      <Rule Name="sFaultNRTMsgLibn" Query="($n2DigitVersion=12 or $n2DigitVersion=14) and $nFaultNRTMsgLibn&gt;0" Error="Error" P0="$nFaultNRTMsgLibn" Title="Outlook crashing issue with NRTMsgLibn.dll found" Text="A crashing issue in Outlook.exe that was caused by NRTMsgLibn.dll was found {0} times in the application event log over the last 14 days. Please click the 'Click here ...' link below for details." GUID="329810" SSID="13a3044c-3c89-48ec-89ff-011ebd04740b" Symptoms="Crash,Add-ins,Error message,Event Log"/>

      <Rule Name="sOutlookCrashFound12" Query="$n2DigitVersion=12 and $nCrashCount!=0" Error="None" Title="One or more crashing events for Outlook found in the Application Event log" Text="At least one crashing event for Outlook was found in the Application Event log. To possibly address this issue, we recommend you check your scan results for known crashing issues and resolve any that are found. If Outlook continues to crash:&#xA;&#xA;1. Make sure Outlook is up-to-date (check your OffCAT report).&#xA;2. Try disabling COM add-ins&#xA;&#xA;For additional troubleshooting techniques, click the 'Tell me more...' link and skip to the 'Can you reproduce the problem' section in the referenced article." GUID="267388" SSID="cf69b297-f49b-46a1-bb55-df71c8fa1cfe" Symptoms="Crash,Error message,Event Log"></Rule>
      <Rule Name="sOutlookCrashFound1415" Query="($n2DigitVersion=14 or $n2DigitVersion=15) and $nCrashCount!=0" Error="None" Title="One or more crashing events for Outlook found in the Application Event log" Text="At least one crashing event for Outlook was found in the Application Event log. To possibly address this issue, we recommend you check your scan results for known crashing issues and resolve any that are found. If Outlook continues to crash:&#xA;&#xA;1. Make sure Outlook is up-to-date (check your OffCAT report).&#xA;2. Try disabling COM add-ins&#xA;&#xA;For additional troubleshooting techniques, click the 'Tell me more...' link and skip to Step 3 in the referenced article." GUID="267389" SSID="a2d6d95e-45c3-4e82-88af-611380eb79b5" Symptoms="Crash,Error message,Event Log"></Rule>

      <Rule Name="nKB2931904Crash" Query="count(../Instance/Setting[@Key1='Fault offset' and (lower-case(Value)='00025b09')])"></Rule>
      <Rule Name="sKB2931904CrashMSI" Query="$n2DigitVersion=15 and $nInstallType='MSI' and $OfficeUpdates_sOffice2013SP1NotInstalled and $nKB2931904Crash&gt;0" Error="Error" P0="$nKB2931904Crash" Title="Crashing issue when using the Calendar found in your application event log {0} times" Text="When you use your Outlook calendar the application may unexpectedly crash. This is a known issue that has been fixed.&#xA;&#xA;Please click the 'Click here ...' link below for information on installing this fix." GUID="391414" SSID="2cfbc5f0-f964-4f55-b56e-3d1acb0fea34" Symptoms="Crash,Meetings or appointments,Event Log"></Rule>
      <Rule Name="sKB2931904CrashC2R" Query="$n2DigitVersion=15 and $nInstallType='ClickToRun' and versioncompare($C2R_Updates_fInstalledC2RVersion,'15.0.4569.1507')&lt;0 and $nKB2931904Crash&gt;0" Error="Error" P0="$nKB2931904Crash" Title="Crashing issue when using the Calendar found in your application event log {0} times" Text="When you use your Outlook calendar the application may unexpectedly crash. This is a known issue that has been fixed.&#xA;&#xA;Please click the 'Click here ...' link below for information on installing this fix." GUID="391414" SSID="ab2497c3-771b-4fe5-afcb-16154d8cefac" Symptoms="Crash,Meetings or appointments,Event Log"></Rule>

      <Rule Name="nKB2935154CrashMod0000" Query="count(../Instance[Setting[@Key1='Faulting Module Version' and (Value='0.0.0.0')] and Setting[@Key1='Fault offset' and ((lower-case(Value)='00862a1b') or (lower-case(Value)='004429bb') or (lower-case(Value)='003729bb') or (lower-case(Value)='00142b73') or (lower-case(Value)='00192b73'))]])"></Rule>
      <Rule Name="nKB2935154CrashMod45511004" Query="count(../Instance[Setting[@Key1='Faulting Module Version' and (Value='15.0.4551.1004')] and Setting[@Key1='Fault offset' and ((lower-case(Value)='00b329bb') or (lower-case(Value)='006229c4') or (lower-case(Value)='003529c2') or (lower-case(Value)='009d29bb') or (lower-case(Value)='002f29bb'))]])"></Rule>
      <Rule Name="nKB2935154CrashMod44201017" Query="count(../Instance[Setting[@Key1='Faulting Module Version' and (Value='15.0.4420.1017')] and Setting[@Key1='Fault offset' and ((lower-case(Value)='00b92b73') or (lower-case(Value)='00272b79'))]])"></Rule>
      <Rule Name="nKB2935154CrashMod45511511" Query="count(../Instance[Setting[@Key1='Faulting Module Version' and (Value='15.0.4551.1511')] and Setting[@Key1='Fault offset' and (lower-case(Value)='002529ab')]])"></Rule>
      <Rule Name="nKB2935154CrashMod45691503" Query="count(../Instance[Setting[@Key1='Faulting Module Version' and (Value='15.0.4569.1503')] and Setting[@Key1='Fault offset' and (lower-case(Value)='00365ec0')]])"></Rule>
      <Rule Name="sKB2935154Crash" Query="$n2DigitVersion=15 and ($nKB2935154CrashMod45691503&gt;0 or $nKB2935154CrashMod0000&gt;0 or $nKB2935154CrashMod45511004&gt;0 or $nKB2935154CrashMod44201017&gt;0 or $nKB2935154CrashMod45511511&gt;0)" Error="Error" Title="Known crashing issue (KB 2935154) detected" Text="The crashing issue documented in KB 2935154 has been detected. Please click the 'Click here ...' link below to see the most recent details on this issue." GUID="392319" SSID="d9a0921f-d049-4ac3-8cf7-3beffb9e0de1" Symptoms="Crash,Startup,Cached mode,Email message display,Junk email"></Rule>

      <Rule Name="nKB2936309CrashMod45511004" Query="count(../Instance[Setting[@Key1='Faulting Module Version' and (Value='15.0.4551.1004')] and Setting[@Key1='Fault offset' and (lower-case(Value)='0030a181')]])"></Rule>
      <Rule Name="nKB2936309CrashMod45691503" Query="count(../Instance[Setting[@Key1='Faulting Module Version' and (Value='15.0.4569.1503')] and Setting[@Key1='Fault offset' and (lower-case(Value)='00356dde')]])"></Rule>
      <Rule Name="nKB2936309CrashMod45511511" Query="count(../Instance[Setting[@Key1='Faulting Module Version' and (Value='15.0.4551.1511')] and Setting[@Key1='Fault offset' and (lower-case(Value)='0030a1a9')]])"></Rule>
      <Rule Name="sKB2936309Crash" Query="$n2DigitVersion=15 and versioncompare($sFullAppVersion,'15.0.4605.1000 ')&lt;0 and ($nKB2936309CrashMod45511004&gt;0 or $nKB2936309CrashMod45691503&gt;0 or $nKB2936309CrashMod45511511&gt;0)" Error="Error" Title="Known crashing issue when collapsing calendar groups detected (KB 2936309) " Text="The crashing issue that occurs when you collapse a calendar group (documented in KB 2936309) has been detected. Please click the 'Click here ...' link below to get the update that resolves this problem." GUID="392546" SSID="9b99a08a-8487-4e75-a1fb-400736e74bbc" Symptoms="Crash,Freeze,Calendar,Meetings or appointments"></Rule>

      <Rule Name="nKB2817468Crash" Query="count(../Instance[Setting[@Key1='Faulting Module Version' and (Value='15.0.4517.1003')] and Setting[@Key1='Fault offset' and (lower-case(Value)='003ac9b5')]])"></Rule>
      <Rule Name="sKB2817468Crash" Query="$nInstallType='MSI' and $OfficeUpdates_sOutlook2013CU=true() and $n2DigitVersion=15 and $nKB2817468Crash&gt;0" Error="Error" P0="$nKB2817468Crash" Title="A known crashing issue listed in KB 2817468 was detected" Text="A known crashing issue noted in KB article 2817468 was detected in your application event log {0} times. This issue is fixed in later builds of Outlook. Please click the 'Click here...' link below to download the latest version." GUID="393281" SSID="0362b083-7223-4379-b794-45402ba65edd" Symptoms="Crash,Event Log"></Rule>
      <Rule Name="sKB2817468CrashC2R" Query="$nInstallType='ClickToRun' and $C2R_Updates_sLatestC2RVersionNotInstalled15=true() and $n2DigitVersion=15 and $nKB2817468Crash&gt;0" Error="Error" P0="$nKB2817468Crash" Title="A known crashing issue listed in KB 2817468 was detected" Text="A known crashing issue noted in KB article 2817468 was detected in your application event log {0} times. This issue is fixed in a recent update for Outlook. Please click the 'Click here...' link below to download the latest update." GUID="392601" SSID="39cfdf9e-8ce8-44e1-8ad4-6476ededf36b" Symptoms="Crash,Event Log"></Rule>

      <Rule Name="n_337015023Crash" Query="count(../Instance[Setting[@Key1='Faulting Module Version' and (Value='15.0.4551.1004')] and Setting[@Key1='Fault offset' and (lower-case(Value)='0004b33a')] and Setting[@Key1='Faulting Module Name' and (lower-case(Value)='outlmime.dll')]])"></Rule>
      <Rule Name="s_337015023Crash" Query="$nInstallType='MSI' and $MSO_fC2R2013SP1UpdateInstalled != true() and $n2DigitVersion=15 and $n_337015023Crash&gt;0" Error="Error" P0="$n_337015023Crash" Title="A known crashing issue was detected in the application event log" Text="A known crashing issue was detected in your application event log {0} times. This issue is fixed in Office 2013 Service Pack 1. Please click the 'Click here...' link below to download Service Pack 1." GUID="392756" SSID="dee82777-31a0-4985-a18c-65a93ca54736" Symptoms="Crash,Event Log,IMAP"></Rule>
      <Rule Name="s_337015023CrashC2R" Query="$nInstallType='ClickToRun' and $MSO_fC2R2013SP1UpdateInstalled != true() and $n2DigitVersion=15 and $n_337015023Crash&gt;0" Error="Error" P0="$n_337015023Crash" Title="A known crashing issue was detected in the application event log" Text="A known crashing issue was detected in your application event log {0} times. This issue is fixed in a recent update for Outlook. Please click the 'Click here...' link below to download the latest update." GUID="392597" SSID="5b051c41-1ead-4399-ab31-97ac3668a5fa" Symptoms="Crash,Event Log,IMAP"></Rule>

      <Rule Name="n_786632546Crash1" Query="count(../Instance[Setting[@Key1='Faulting Module Version' and (Value='15.0.4481.1000')] and Setting[@Key1='Fault offset' and (lower-case(Value)='0009fc10')] and Setting[@Key1='Faulting Module Name' and (lower-case(Value)='olmapi32.dll')]])"></Rule>
      <Rule Name="n_786632546Crash2" Query="count(../Instance[Setting[@Key1='Faulting Module Version' and (Value='15.0.4551.1003')] and Setting[@Key1='Fault offset' and (lower-case(Value)='0009fbac')] and Setting[@Key1='Faulting Module Name' and (lower-case(Value)='olmapi32.dll')]])"></Rule>
      <Rule Name="s_786632546Crash" Query="$nInstallType='MSI' and $MSO_fC2R2013SP1UpdateInstalled != true() and $n2DigitVersion=15 and ($n_786632546Crash1&gt;0 or $n_786632546Crash2&gt;0)" Error="Error" P0="$n_786632546Crash1 + $n_786632546Crash2" Title="A known crashing issue was detected in the application event log" Text="A known crashing issue was detected in your application event log {0} times. This issue is fixed in Office 2013 Service Pack 1. Please click the 'Click here...' link below to download Service Pack 1." GUID="392759" SSID="24b831f1-929f-4fb1-825c-a562e04c120a" Symptoms="Crash,Event Log"></Rule>
      <Rule Name="s_786632546CrashC2R" Query="$nInstallType='ClickToRun' and $MSO_fC2R2013SP1UpdateInstalled != true() and $n2DigitVersion=15 and ($n_786632546Crash1&gt;0 or $n_786632546Crash2&gt;0)" Error="Error" P0="$n_786632546Crash1 + $n_786632546Crash2" Title="A known crashing issue was detected in the application event log" Text="A known crashing issue was detected in your application event log {0} times. This issue is fixed in a recent update for Outlook. Please click the 'Click here...' link below to download the latest update." GUID="392648" SSID="5f44f9c4-5c82-405d-a68d-fa9d0bc24257" Symptoms="Crash,Event Log"></Rule>

      <Rule Name="n144163489Crash" Query="count(../Instance[Setting[@Key1='Faulting Module Version' and (Value='7.0.9200.16384')] and Setting[@Key1='Fault offset' and (lower-case(Value)='0000000000001273')] and Setting[@Key1='Faulting Module Name' and (lower-case(Value)='msvcrt.dll')]])"></Rule>
      <Rule Name="s144163489Crash" Query="$nInstallType='MSI' and $MSO_fC2R2013SP1UpdateInstalled != true() and $n2DigitVersion=15 and $n144163489Crash&gt;0" Error="Error" P0="$n144163489Crash" Title="A known crashing issue was detected in the application event log" Text="A known crashing issue was detected in your application event log {0} times. This issue is fixed in Office 2013 Service Pack 1. Please click the 'Click here...' link below to download Service Pack 1." GUID="392757" SSID="1743933f-925a-4c63-b53e-f0bc6e97eeb2" Symptoms="Crash,Event Log"></Rule>
      <Rule Name="s144163489CrashC2R" Query="$nInstallType='ClickToRun' and $MSO_fC2R2013SP1UpdateInstalled != true() and $n2DigitVersion=15 and $n144163489Crash&gt;0" Error="Error" P0="$n144163489Crash" Title="A known crashing issue was detected in the application event log" Text="A known crashing issue was detected in your application event log {0} times. This issue is fixed in a recent update for Outlook. Please click the 'Click here...' link below to download the latest update." GUID="392648" SSID="54d2b7e1-25c4-4149-ae2a-09009468809e" Symptoms="Crash,Event Log"></Rule>

      <Rule Name="n99561905Crash" Query="count(../Instance[Setting[@Key1='Faulting Module Version' and (Value='15.0.4481.1001')] and Setting[@Key1='Fault offset' and (lower-case(Value)='0000000000734ea4')] and Setting[@Key1='Faulting Module Name' and (lower-case(Value)='mso.dll')]])"></Rule>
      <Rule Name="s99561905Crash" Query="$nInstallType='MSI' and $MSO_fC2R2013SP1UpdateInstalled != true() and $n2DigitVersion=15 and $n99561905Crash&gt;0" Error="Error" P0="$n99561905Crash" Title="A known crashing issue was detected in the application event log" Text="A known crashing issue was detected in your application event log {0} times. This issue is fixed in Office 2013 Service Pack 1. Please click the 'Click here...' link below to download Service Pack 1." GUID="392758" SSID="973736d4-4128-4bd2-8aa6-a6a4f2e856f1" Symptoms="Crash,Event Log"></Rule>
      <Rule Name="s99561905CrashC2R" Query="$nInstallType='ClickToRun' and $MSO_fC2R2013SP1UpdateInstalled != true() and $n2DigitVersion=15 and $n99561905Crash&gt;0" Error="Error" P0="$n99561905Crash" Title="A known crashing issue was detected in the application event log" Text="A known crashing issue was detected in your application event log {0} times. This issue is fixed in a recent update for Outlook. Please click the 'Click here...' link below to download the latest update." GUID="392650" SSID="7691ac98-f405-4b51-947c-c360f756571d" Symptoms="Crash,Event Log"></Rule>

      <Rule Name="n3383638Msvcr100Crash" Query="count(../Instance[Setting[@Key1='Fault offset' and (lower-case(Value)='00002014')] and Setting[@Key1='Faulting Module Name' and (lower-case(Value)='msvcr100.dll')]])"></Rule>
      <Rule Name="s3383638Msvcr100Crash" Query="$nInstallType='MSI' and versioncompare($sFullAppVersion,'15.0.4551.1511')&lt;0 and $n2DigitVersion=15 and $n3383638Msvcr100Crash&gt;0" Error="Error" P0="$n3383638Msvcr100Crash" Title="A known crashing issue (working in the Calendar) was detected" Text="A known crash that can occur working with recurring meetings was detected in your application event log {0} times. This issue is fixed in a build of Outlook that is more recent than the one you have installed. Please click the 'Click here...' link below, and then install the update under the 'Outlook (global) update' section of the article." GUID="397842" SSID="2d3b9147-5e1f-4d6d-b301-10cd3ce937f9" Symptoms="Calendar,Crash,Event Log,Meetings or appointments"></Rule>
      <Rule Name="s3383638Msvcr100CrashC2R" Query="$nInstallType='ClickToRun' and versioncompare($sFullAppVersion,'15.0.4551.1511')&lt;0 and $n2DigitVersion=15 and $n3383638Msvcr100Crash&gt;0" Error="Error" P0="$n3383638Msvcr100Crash" Title="A known crashing issue (working in the Calendar) was detected" Text="A known crash that can occur working with recurring meetings was detected in your application event log {0} times. This issue is fixed in a build of Outlook that is more recent than the one you have installed. Please click the 'Click here...' link below and then follow the instructions to get the latest Click-to-run update installed." GUID="398736" SSID="cead3703-da52-49f4-aae7-44859d1bd118" Symptoms="Calendar,Crash,Event Log,Meetings or appointments"></Rule>

      <Rule Name="nKB2964409CrashMod47601000" Query="count(../Instance[Setting[@Key1='Faulting Module Version' and (Value='14.0.4760.1000')] and Setting[@Key1='Fault offset' and (lower-case(Value)='0001174a')]])"></Rule>
      <Rule Name="nKB2964409CrashMod70121000" Query="count(../Instance[Setting[@Key1='Faulting Module Version' and (Value='14.0.7012.1000')] and Setting[@Key1='Fault offset' and (lower-case(Value)='0000000000202d0e')]])"></Rule>
      <Rule Name="nKB2964409CrashMod71095000" Query="count(../Instance[Setting[@Key1='Faulting Module Version' and (Value='14.0.7109.5000')] and Setting[@Key1='Fault offset' and (lower-case(Value)='00b00bab')]])"></Rule>
      <Rule Name="nKB2964409CrashMod61175001" Query="count(../Instance[Setting[@Key1='Faulting Module Version' and (Value='14.0.6117.5001')] and Setting[@Key1='Fault offset' and (lower-case(Value)='00af9aac')]])"></Rule>
      <Rule Name="sKB2964409Crash" Query="$n2DigitVersion=14 and ($nKB2964409CrashMod47601000&gt;0 or $nKB2964409CrashMod70121000&gt;0 or $nKB2964409CrashMod71095000&gt;0 or $nKB2964409CrashMod61175001&gt;0)" Error="Error" Title="Known crashing issue when corrupted views detected (KB 2964409) " Text="The crashing issue that occurs when corrupted views (documented in KB 2964409) has been detected. Please click the 'Click here ...' link below to see the most recent details on this issue." GUID="392865" SSID="e06586ad-1f95-46a8-ad2a-eee19615d087" Symptoms="Crash,Freeze,Calendar,Meetings or appointments"></Rule>

      <Rule Name="nKB2964632CrashMod960016496" Query="count(../Instance[Setting[@Key1='Faulting Module Version' and (Value='6.3.9600.16496')] and Setting[@Key1='Fault offset' and (lower-case(Value)='00012eec')] and Setting[@Key1='Faulting Module Name' and (lower-case(Value)='kernelbase.dll')]])"></Rule>
      <Rule Name="nKB2964632CrashMod960017031" Query="count(../Instance[Setting[@Key1='Faulting Module Version' and (Value='6.3.9600.17031')] and Setting[@Key1='Fault offset' and (lower-case(Value)='00014dbd')] and Setting[@Key1='Faulting Module Name' and (lower-case(Value)='kernelbase.dll')]])"></Rule>
      <Rule Name="nKB2964632CrashMod960016408" Query="count(../Instance[Setting[@Key1='Faulting Module Version' and (Value='6.3.9600.16408')] and Setting[@Key1='Fault offset' and (lower-case(Value)='00012eec')] and Setting[@Key1='Faulting Module Name' and (lower-case(Value)='kernelbase.dll')]])"></Rule>
      <Rule Name="nKB2964632CrashMod920016857" Query="count(../Instance[Setting[@Key1='Faulting Module Version' and (Value='6.2.9200.16857')] and Setting[@Key1='Fault offset' and (lower-case(Value)='00010f22')] and Setting[@Key1='Faulting Module Name' and (lower-case(Value)='kernelbase.dll')]])"></Rule>
      <Rule Name="nKB2964632CrashMod760118229" Query="count(../Instance[Setting[@Key1='Faulting Module Version' and (Value='6.1.7601.18229')] and Setting[@Key1='Fault offset' and (lower-case(Value)='0000c41f')] and Setting[@Key1='Faulting Module Name' and (lower-case(Value)='kernelbase.dll')]])"></Rule>
      <Rule Name="sKB2964632Crash" Query="$nInstallType='MSI' and $MSO_fC2R2013SP1UpdateInstalled != true() and $n2DigitVersion=15 and ($nKB2964632CrashMod960016496&gt;0 or $nKB2964632CrashMod960017031&gt;0 or $nKB2964632CrashMod960016408&gt;0 or $nKB2964632CrashMod920016857&gt;0 or $nKB2964632CrashMod760118229&gt;0)" Error="Error" P0="($nKB2964632CrashMod960016496 + $nKB2964632CrashMod960017031 + $nKB2964632CrashMod960016408 + $nKB2964632CrashMod920016857 + $nKB2964632CrashMod760118229)" Title="Known crashing issue when corrupted meeting detected (KB 2964632)" Text="The crashing issue that occurs when corrupted meeting (documented in KB 2964632) has been detected {0} times. Please click the 'Click here...' link below to see the most recent details on this issue." GUID="397742" SSID="384beff6-18cb-494e-b87a-ba7ea3da6994" Symptoms="Crash,Freeze,Calendar,Meetings or appointments"></Rule>
      <Rule Name="sKB2964632CrashC2R" Query="$nInstallType='ClickToRun' and $MSO_fC2R2013SP1UpdateInstalled != true() and $n2DigitVersion=15 and ($nKB2964632CrashMod960016496&gt;0 or $nKB2964632CrashMod960017031&gt;0 or $nKB2964632CrashMod960016408&gt;0 or $nKB2964632CrashMod920016857&gt;0 or $nKB2964632CrashMod760118229&gt;0)" Error="Error" P0="($nKB2964632CrashMod960016496 + $nKB2964632CrashMod960017031 + $nKB2964632CrashMod960016408 + $nKB2964632CrashMod920016857 + $nKB2964632CrashMod760118229)" Title="Known crashing issue when corrupted meeting detected (KB 2964632)" Text="The crashing issue that occurs when corrupted meeting (documented in KB 2964632) has been detected {0} times. Please click the 'Click here...' link below to see information on installing the latest Click-to-run update." GUID="397742" SSID="e525cd77-fc7d-4831-88d7-678a837e8edd" Symptoms="Crash,Freeze,Calendar,Meetings or appointments"></Rule>

      <Rule Name="n3422496CrashMod15046051000" Query="count(../Instance[Setting[@Key1='Faulting Module Version' and (Value='15.0.4605.1000')] and Setting[@Key1='Fault offset' and (lower-case(Value)='00d2782a')] and Setting[@Key1='Faulting Module Name' and (lower-case(Value)='outlook.exe')]])"></Rule>
      <Rule Name="n3422496CrashMod15045691503" Query="count(../Instance[Setting[@Key1='Faulting Module Version' and (Value='15.0.4569.1503')] and Setting[@Key1='Fault offset' and (lower-case(Value)='00d2585a')] and Setting[@Key1='Faulting Module Name' and (lower-case(Value)='outlook.exe')]])"></Rule>
      <Rule Name="s3422496Crash" Query="$n2DigitVersion=15 and ($n3422496CrashMod15046051000&gt;0 or $n3422496CrashMod15045691503&gt;0)" Error="Error" P0="$n3422496CrashMod15046051000 + $n3422496CrashMod15045691503" Title="A known crashing issue that can occur when opening messages from the reading pane was detected" Text="The crashing issue that is documented in KB 2976096 has been detected {0} times. Please click the 'Click here ...' link below for details on a resolution to this issue." GUID="402093" SSID="95eed9ea-bc5e-4540-b70e-934cf029cba9" Symptoms="Crash,Event Log"></Rule>

      <Rule Name="n3449397CrashMod15046211000" Query="count(../Instance[Setting[@Key1='Faulting Module Version' and (Value='15.0.4621.1000')] and Setting[@Key1='Fault offset' and (lower-case(Value)='000a8608')] and Setting[@Key1='Faulting Module Name' and (lower-case(Value)='pstprx32.dll')]])"></Rule>
      <Rule Name="s3449397CrashMod15046211000" Query="$n2DigitVersion=15 and versioncompare($sFullAppVersion,'15.0.4631.1000')&lt;0 and $n3449397CrashMod15046211000&gt;0" Error="Error" P0="$n3449397CrashMod15046211000" Title="A known crashing issue while synchronizing a corrupt calendar item for an Outlook.com account has been detected" Text="The crashing issue that occurs when synchronizing a corrupt calendar item for an Outlook.com account has been detected {0} times. Please click the 'Click here ...' link below to obtain a fix for this issue." GUID="403187" SSID="4c3f3d5e-2258-4194-bc5b-d7afbfc75213" Symptoms="Crash,Event Log"></Rule>

      <Rule Name="nFaultA2xAddin0x0000936d" Query="count(../Instance[Setting[@Key1='Faulting Module Version' and (Value='1.0.0.1')] and Setting[@Key1='Fault offset' and (lower-case(Value)='0000936d')] and Setting[@Key1='Faulting Module Name' and (lower-case(Value)='a2xaddin.dll')]])"></Rule>
      <Rule Name="sFaultA2xAddin0x0000936d" Query="$n2DigitVersion=14 and $nFaultA2xAddin0x0000936d&gt;0" Error="Error" P0="$nFaultA2xAddin0x0000936d" Title="Outlook crashing issue with A2xAddin.dll found" Text="A crashing issue in Outlook.exe that was caused by A2xAddin.dll was found {0} times in the application event log over the last 14 days. This problem has been known to be caused by Able2Extract software.&#xA;&#xA;Please click the 'Click here ...' link below for details." GUID="397967" SSID="de96a7c0-9979-44cc-8b21-aef76ed1ba19" Symptoms="Add-ins,Crash,Error message,Freeze"></Rule>

      <Rule Name="nCrashIgd10umd32Outlook" Query="count(../Instance[Setting[@Key1='Faulting Module Name' and (lower-case(Value)='igd10umd32.dll')]])"></Rule>
      <Rule Name="sCrashIgd10umd32Outlook" Query="$n2DigitVersion=15 and $nCrashIgd10umd32Outlook&gt;0" Error="Error" P0="$nCrashIgd10umd32Outlook" Title="Outlook crashing issue with Igd10mud32.dll found" Text="A crashing issue in Outlook.exe that was caused by Igd10umd32.dll was found {0} times in the application event log. This problem has been known to be caused by an outdated Intel graphics accelerator driver.&#xA;&#xA;Please click the 'Click here ...' link below for details." GUID="404006" SSID="4edcc401-8555-45f1-80fe-27950e1b904d" Symptoms="Crash,Error message,Event Log"></Rule>

      <Rule Name="n3427850Crash_382383016" Query="count(../Instance[Setting[@Key1='Faulting Module Version' and (Value='15.0.4535.1507')] and Setting[@Key1='Fault offset' and (lower-case(Value)='00096cc0')] and Setting[@Key1='Faulting Module Name' and (lower-case(Value)='wwlib.dll')]])"></Rule>
      <Rule Name="n3427850Crash73263998663" Query="count(../Instance[Setting[@Key1='Faulting Module Version' and (Value='15.0.4615.1000')] and Setting[@Key1='Fault offset' and (lower-case(Value)='00097451')] and Setting[@Key1='Faulting Module Name' and (lower-case(Value)='wwlib.dll')]])"></Rule>
      <Rule Name="n3427850Crash73196258780" Query="count(../Instance[Setting[@Key1='Faulting Module Version' and (Value='15.0.4605.1001')] and Setting[@Key1='Fault offset' and (lower-case(Value)='000972d2')] and Setting[@Key1='Faulting Module Name' and (lower-case(Value)='wwlib.dll')]])"></Rule>
      <Rule Name="n3427850Crash73121181932" Query="count(../Instance[Setting[@Key1='Faulting Module Version' and (Value='15.0.4569.1504')] and Setting[@Key1='Fault offset' and (lower-case(Value)='0009709f')] and Setting[@Key1='Faulting Module Name' and (lower-case(Value)='wwlib.dll')]])"></Rule>
      <Rule Name="s3427850CrashModWwlib" Query="$n2DigitVersion=15 and versioncompare($sFullAppVersion,'15.0.4631.1000')&lt;0 and ($n3427850Crash_382383016&gt;0 or $n3427850Crash73263998663&gt;0 or $n3427850Crash73196258780&gt;0 or $n3427850Crash73121181932&gt;0)" Error="Error" P0="$n3427850Crash_382383016 + $n3427850Crash73263998663 + $n3427850Crash73196258780 + $n3427850Crash73121181932" Title="A known crashing issue that occurs when replying to a message for voice mail has been detected" Text="The crashing issue that occurs when replying to a message for voice mail has been detected {0} times. Please click the 'Click here ...' link below to obtain the fix for this issue." GUID="404209" SSID="e372bf15-2a03-4290-8332-4022615ceacc" Symptoms="Crash"></Rule>

      <Rule Name="n3459258MsoCrashOutlook00003ABC" Query="count(../Instance[Setting[@Key1='Faulting Module Version' and (Value='15.0.4631.1000')] and Setting[@Key1='Fault offset' and (lower-case(Value)='00003abc')] and Setting[@Key1='Faulting Module Name' and (lower-case(Value)='mso.dll')]])"></Rule>
      <Rule Name="n3459258MsoCrashOutlook0000329C" Query="count(../Instance[Setting[@Key1='Faulting Module Version' and (Value='0.0.0.0')] and Setting[@Key1='Fault offset' and (lower-case(Value)='0000329c')] and Setting[@Key1='Faulting Module Name' and (lower-case(Value)='mso.dll')]])"></Rule>
      <Rule Name="s3459258MsoCrashOutlookX86" Query="not($MSO_fMsoAug2014UpdateInstalled) and $nInstallType='MSI' and $n2DigitVersion=15 and $bitness='x86' and ($n3459258MsoCrashOutlook00003ABC&gt;0 or $n3459258MsoCrashOutlook0000329C&gt;0)" Error="Error" P0="$n3459258MsoCrashOutlook00003ABC + $n3459258MsoCrashOutlook0000329C" Title="Known crashing issue when Outlook stops responding or crashes (KB 2987489)" Text="The crashing issue that occurs when Outlook stops responding or crashes (documented in KB 2987489) has been detected {0} time(s). Please click the 'Click here...' link below to see how to resolve this issue." GUID="506809" SSID="6789516e-3fac-4614-9901-617fd3ad3466" Symptoms="Crash"></Rule>
      <Rule Name="n3459258MsoCrashOutlook00000000013F766E" Query="count(../Instance[Setting[@Key1='Faulting Module Version' and (Value='15.0.4631.1000')] and Setting[@Key1='Fault offset' and (lower-case(Value)='00000000013f766e')] and Setting[@Key1='Faulting Module Name' and (lower-case(Value)='mso.dll')]])"></Rule>
      <Rule Name="n3459258MsoCrashOutlook00000000013EB86E" Query="count(../Instance[Setting[@Key1='Faulting Module Version' and (Value='0.0.0.0')] and Setting[@Key1='Fault offset' and (lower-case(Value)='00000000013eb86e')] and Setting[@Key1='Faulting Module Name' and (lower-case(Value)='mso.dll')]])"></Rule>
      <Rule Name="s3459258MsoCrashOutlookX64" Query="not($MSO_fMsoAug2014UpdateInstalled) and $nInstallType='MSI' and $n2DigitVersion=15 and $bitness='x64' and ($n3459258MsoCrashOutlook00000000013F766E&gt;0 or $n3459258MsoCrashOutlook00000000013EB86E&gt;0)" Error="Error" P0="$n3459258MsoCrashOutlook00000000013F766E + $n3459258MsoCrashOutlook00000000013EB86E" Title="Known crashing issue when Outlook stops responding or crashes (KB 2987489)" Text="The crashing issue that occurs when Outlook stops responding or crashes (documented in KB 2987489) has been detected {0} time(s). Please click the 'Click here...' link below to see how to resolve this issue." GUID="506826" SSID="f47fa725-7f67-4da8-879b-81a3446e9ace" Symptoms="Crash"></Rule>
      <Rule Name="s3459258MsoCrashOutlookC2R" Query="not($MSO_fMsoAug2014UpdateInstalled) and $nInstallType='ClickToRun' and $n2DigitVersion=15 and ($n3459258MsoCrashOutlook00003ABC&gt;0 or $n3459258MsoCrashOutlook0000329C&gt;0)" Error="Error" P0="$n3459258MsoCrashOutlook00003ABC + $n3459258MsoCrashOutlook0000329C" Title="Known crashing issue when Outlook stops responding or crashes (KB 2987489)" Text="The crashing issue that occurs when Outlook stops responding or crashes (documented in KB 2987489) has been detected {0} time(s). Please click the 'Click here...' link below to see how to resolve this issue." GUID="506827" SSID="73a0f64f-c60c-4e33-9f88-8662333c8fd6" Symptoms="Crash"></Rule>

      <Rule Name="n3441064Crash73192366113" Query="count(../Instance[Setting[@Key1='Faulting Module Version' and (Value='15.0.4605.1000')] and Setting[@Key1='Fault offset' and (lower-case(Value)='000dcd8d')] and Setting[@Key1='Faulting Module Name' and (lower-case(Value)='outlook.exe')]])"></Rule>
      <Rule Name="n3441064Crash73260543145" Query="count(../Instance[Setting[@Key1='Faulting Module Version' and (Value='15.0.4615.1000')] and Setting[@Key1='Fault offset' and (lower-case(Value)='000dd24e')] and Setting[@Key1='Faulting Module Name' and (lower-case(Value)='outlook.exe')]])"></Rule>
      <Rule Name="n3441064Crash73447439052" Query="count(../Instance[Setting[@Key1='Faulting Module Version' and (Value='15.0.4641.1001')] and Setting[@Key1='Fault offset' and (lower-case(Value)='000dd046')] and Setting[@Key1='Faulting Module Name' and (lower-case(Value)='outlook.exe')]])"></Rule>
      <Rule Name="n3441064Crash73375668203" Query="count(../Instance[Setting[@Key1='Faulting Module Version' and (Value='15.0.4631.1000')] and Setting[@Key1='Fault offset' and (lower-case(Value)='000dc3b4')] and Setting[@Key1='Faulting Module Name' and (lower-case(Value)='outlook.exe')]])"></Rule>
      <Rule Name="n3441064Crash73316740048" Query="count(../Instance[Setting[@Key1='Faulting Module Version' and (Value='15.0.4623.1000')] and Setting[@Key1='Fault offset' and (lower-case(Value)='000dc9c6')] and Setting[@Key1='Faulting Module Name' and (lower-case(Value)='outlook.exe')]])"></Rule>
      <Rule Name="n3441064Crash73109552091" Query="count(../Instance[Setting[@Key1='Faulting Module Version' and (Value='15.0.4569.1503')] and Setting[@Key1='Fault offset' and (lower-case(Value)='000d9f0c')] and Setting[@Key1='Faulting Module Name' and (lower-case(Value)='outlook.exe')]])"></Rule>
      <Rule Name="s3441064CrashMSI" Query="$nInstallType='MSI' and versioncompare($sFullAppVersion,'15.0.4649.1000')&lt;0 and ($n3441064Crash73109552091&gt;0 or $n3441064Crash73192366113&gt;0 or $n3441064Crash73260543145&gt;0 or $n3441064Crash73447439052&gt;0 or $n3441064Crash73375668203&gt;0 or $n3441064Crash73316740048&gt;0)" Error="Error" P0="$n3441064Crash73109552091 + $n3441064Crash73192366113 + $n3441064Crash73260543145 + $n3441064Crash73447439052 + $n3441064Crash73375668203 + $n3441064Crash73316740048" Title="Known crashing issue when Outlook 2013 crashes while using the scheduling assistant" Text="The crashing issue that is documented in KB 2889873 has been detected {0} time(s). To resolve this problem, please click the 'Click here...' link below and then install the hotfix provided in the article." GUID="511998" SSID="649a2540-d471-4689-83bd-c82e9797c91c" Symptoms="Crash"></Rule>
      <Rule Name="s3441064CrashC2R" Query="$nInstallType='ClickToRun' and versioncompare($C2R_Updates_fInstalledC2RVersion,'15.0.4649.1001')&lt;0 and ($n3441064Crash73109552091&gt;0 or $n3441064Crash73192366113&gt;0 or $n3441064Crash73260543145&gt;0 or $n3441064Crash73447439052&gt;0 or $n3441064Crash73375668203&gt;0 or $n3441064Crash73316740048&gt;0)" Error="Error" P0="$n3441064Crash73109552091 + $n3441064Crash73192366113 + $n3441064Crash73260543145 + $n3441064Crash73447439052 + $n3441064Crash73375668203 + $n3441064Crash73316740048" Title="Known crashing issue when Outlook 2013 crashes while using the scheduling assistant" Text="The crashing issue that is documented in KB 2889873 has been detected {0} time(s). To resolve this problem, please click the 'Click here...' link below and then follow the instructions provided in the article to update your Office installation." GUID="512002" SSID="cef6e1b6-8e72-4c1f-83a4-2b870e376eca" Symptoms="Crash"></Rule>

      <Rule Name="n3455683Crash73463204584" Query="count(../Instance[Setting[@Key1='Faulting Module Version' and (Value='15.0.4641.1001')] and Setting[@Key1='Fault offset' and (lower-case(Value)='002f46bc')] and Setting[@Key1='Faulting Module Name' and (lower-case(Value)='mso.dll')]])"></Rule>
      <Rule Name="n3455683Crash73264615553" Query="count(../Instance[Setting[@Key1='Faulting Module Version' and (Value='15.0.4615.1000')] and Setting[@Key1='Fault offset' and (lower-case(Value)='002e4adf')] and Setting[@Key1='Faulting Module Name' and (lower-case(Value)='mso.dll')]])"></Rule>
      <Rule Name="s3455683CrashX86MSI" Query="$nInstallType='MSI' and $n2DigitVersion=15 and $bitness='x86' and versioncompare($OfficeUpdates_sWordPS,'15.0.4649.1001')&lt;0 and ($n3455683Crash73463204584&gt;0 or $n3455683Crash73264615553&gt;0)" Error="Error" P0="$n3455683Crash73463204584 + $n3455683Crash73264615553" Title="Known crashing issue when Outlook 2013 crashes opening certain email messages" Text="The crashing issue that is documented in KB 2889881 has been detected {0} time(s). To resolve this problem, please click the 'Click here...' link below and then install the x86 version of the Word hotfix provided in the article." GUID="512147" SSID="115acb65-85bb-4379-b15a-b2c72f3ff3d7" Symptoms="Crash"></Rule>
      <Rule Name="n3455683Crash85942195602" Query="count(../Instance[Setting[@Key1='Faulting Module Version' and (Value='15.0.4631.1000')] and Setting[@Key1='Fault offset' and (lower-case(Value)='000000000028b2f0')] and Setting[@Key1='Faulting Module Name' and (lower-case(Value)='mso.dll')]])"></Rule>
      <Rule Name="s3455683CrashX64MSI" Query="$nInstallType='MSI' and $n2DigitVersion=15 and $bitness='x64' and versioncompare($OfficeUpdates_sWordPS,'15.0.4649.1001')&lt;0 and $n3455683Crash85942195602&gt;0" Error="Error" P0="$n3455683Crash85942195602" Title="Known crashing issue when Outlook 2013 crashes opening certain email messages" Text="The crashing issue that is documented in KB 2889881 has been detected {0} time(s). To resolve this problem, please click the 'Click here...' link below and then install the x64 version of the Word hotfix provided in the article." GUID="512147" SSID="f8a3a2e4-a2d6-4bc8-a476-4369ecd860ae" Symptoms="Crash"></Rule>
      <Rule Name="s3455683CrashC2R" Query="$nInstallType='ClickToRun' and $n2DigitVersion=15 and versioncompare($C2R_Updates_fInstalledC2RVersion,'15.0.4649.1001')&lt;0 and ($n3455683Crash73463204584&gt;0 or $n3455683Crash73264615553&gt;0)" Error="Error" P0="$n3455683Crash73463204584 + $n3455683Crash73264615553" Title="Known crashing issue when Outlook 2013 crashes opening certain email messages" Text="The crashing issue that is documented in KB 2889881 has been detected {0} time(s). To resolve this problem, please click the 'Click here...' link below and then follow the instructions provided in the article to update your Office installation." GUID="512181" SSID="5f1a82e1-d82b-4497-81b8-d306bc3ba51a" Symptoms="Crash"></Rule>

      <Rule Name="n3318331Crash80806110" Query="count(../Instance[Setting[@Key1='Faulting Module Version' and (Value='6.3.9600.17055')] and Setting[@Key1='Fault offset' and (lower-case(Value)='00000000000a43da')] and Setting[@Key1='Faulting Module Name' and (lower-case(Value)='kernelbase.dll')]])"></Rule>
      <Rule Name="n3318331Crash85927669397" Query="count(../Instance[Setting[@Key1='Faulting Module Version' and (Value='6.3.9600.17055')] and Setting[@Key1='Fault offset' and (lower-case(Value)='000b3425')] and Setting[@Key1='Faulting Module Name' and (lower-case(Value)='kernelbase.dll')]])"></Rule>
      <Rule Name="n3318331Crash73026682357" Query="count(../Instance[Setting[@Key1='Faulting Module Version' and (Value='6.1.7601.18229')] and Setting[@Key1='Fault offset' and (lower-case(Value)='00013219')] and Setting[@Key1='Faulting Module Name' and (lower-case(Value)='kernelbase.dll')]])"></Rule>
      <Rule Name="n3318331Crash85956874485" Query="count(../Instance[Setting[@Key1='Faulting Module Version' and (Value='6.3.9600.17278')] and Setting[@Key1='Fault offset' and (lower-case(Value)='00000000000da26a')] and Setting[@Key1='Faulting Module Name' and (lower-case(Value)='kernelbase.dll')]])"></Rule>
      <Rule Name="n3318331Crash73467153257" Query="count(../Instance[Setting[@Key1='Faulting Module Version' and (Value='6.3.9600.16656')] and Setting[@Key1='Fault offset' and (lower-case(Value)='000b33b7')] and Setting[@Key1='Faulting Module Name' and (lower-case(Value)='kernelbase.dll')]])"></Rule>
      <Rule Name="n3318331Crash73465335231" Query="count(../Instance[Setting[@Key1='Faulting Module Version' and (Value='6.3.9600.17055')] and Setting[@Key1='Fault offset' and (lower-case(Value)='000b9dfa')] and Setting[@Key1='Faulting Module Name' and (lower-case(Value)='kernelbase.dll')]])"></Rule>
      <Rule Name="n3318331Crash73448456911" Query="count(../Instance[Setting[@Key1='Faulting Module Version' and (Value='6.3.9600.17031')] and Setting[@Key1='Fault offset' and (lower-case(Value)='000b34c5')] and Setting[@Key1='Faulting Module Name' and (lower-case(Value)='kernelbase.dll')]])"></Rule>
      <Rule Name="n3318331Crash73507790552" Query="count(../Instance[Setting[@Key1='Faulting Module Version' and (Value='6.3.9600.17278')] and Setting[@Key1='Fault offset' and (lower-case(Value)='000b3c5f')] and Setting[@Key1='Faulting Module Name' and (lower-case(Value)='kernelbase.dll')]])"></Rule>
      <Rule Name="n3318331Crash73452455029" Query="count(../Instance[Setting[@Key1='Faulting Module Version' and (Value='6.3.9600.16384')] and Setting[@Key1='Fault offset' and (lower-case(Value)='000b2bcd')] and Setting[@Key1='Faulting Module Name' and (lower-case(Value)='kernelbase.dll')]])"></Rule>
      <Rule Name="n3318331Crash85953438027" Query="count(../Instance[Setting[@Key1='Faulting Module Version' and (Value='6.3.9600.16408')] and Setting[@Key1='Fault offset' and (lower-case(Value)='00000000000d9532')] and Setting[@Key1='Faulting Module Name' and (lower-case(Value)='kernelbase.dll')]])"></Rule>
      <Rule Name="s3318331Crash" Query="$n2DigitVersion=15 and ($n3318331Crash80806110&gt;0 or $n3318331Crash85927669397&gt;0 or $n3318331Crash73026682357&gt;0 or $n3318331Crash85956874485&gt;0 or $n3318331Crash73467153257&gt;0 or $n3318331Crash73465335231&gt;0 or $n3318331Crash73448456911&gt;0 or $n3318331Crash73507790552&gt;0 or $n3318331Crash73452455029&gt;0 or $n3318331Crash85953438027&gt;0)" Error="Error" P0="$n3318331Crash80806110 + $n3318331Crash85927669397 + $n3318331Crash73026682357 + $n3318331Crash85956874485 + $n3318331Crash73467153257 + $n3318331Crash73465335231 + $n3318331Crash73448456911 + $n3318331Crash73507790552 + $n3318331Crash73452455029 + $n3318331Crash85953438027" Title="Outlook crashes when you have a corrupted .pst or .ost file" Text="The crashing issue that is documented in KB 3002649 has been detected {0} time(s). To resolve this problem, please click the 'Click here...' link below and then follow the instructions provided in the article." GUID="512181" SSID="5f1a82e1-d82b-4497-81b8-d306bc3ba51a" Symptoms="Crash"></Rule>

      <Rule Name="n3424449CrashSecManOutlook" Query="count(../Instance[Setting[@Key1='Faulting Module Name' and (lower-case(Value)='secman.dll')]])"></Rule>
      <Rule Name="s3424449CrashSecManDll" Query="$n2DigitVersion=15 and $n3424449CrashSecManOutlook&gt;0" Error="Error" P0="$n3424449CrashSecManOutlook" Title="Outlook crashing issue with Secman.dll has been detected" Text="The crashing issue that occurs when Secman.dll is installed has been detected {0} times. Please click the 'Click here...' link below to see how to resolve this issue." GUID="509795" SSID="289eb95a-60dd-4a6d-811a-2d6259af2b43" Symptoms="Crash"></Rule>

      <Rule Name="n3424163Crash228059666" Query="count(../Instance[Setting[@Key1='Faulting Module Version' and (Value='15.0.4569.1503')] and Setting[@Key1='Fault offset' and (lower-case(Value)='0018fed')] and Setting[@Key1='Faulting Module Name' and (lower-case(Value)='emsmdb32.dll')]])"></Rule>
      <Rule Name="n3424163Crash85950190501" Query="count(../Instance[Setting[@Key1='Faulting Module Version' and (Value='15.0.4641.1001')] and Setting[@Key1='Fault offset' and (lower-case(Value)='00000000001d0cc5')] and Setting[@Key1='Faulting Module Name' and (lower-case(Value)='emsmdb32.dll')]])"></Rule>
      <Rule Name="s3424163CrashX86MSI" Query="$nInstallType='MSI' and $n2DigitVersion=15 and $bitness='x86' and versioncompare($sEmsmdb322013Version,'15.0.4659.1000')&lt;0 and ($n3424163Crash228059666&gt;0)" Error="Error" P0="$n3424163Crash228059666" Title="Known crashing issue when Outlook 2013 crashes opening certain email messages" Text="The crashing issue that is documented in KB 2889951 has been detected {0} time(s). To resolve this problem, please click the 'Click here...' link below and then install the x86 version of the hotfix provided in the article." GUID="517526" SSID="48586690-abce-4900-aae0-df701f55c236" Symptoms="Crash"></Rule>
      <Rule Name="s3424163CrashX64MSI" Query="$nInstallType='MSI' and $n2DigitVersion=15 and $bitness='x64' and versioncompare($sEmsmdb322013Version,'15.0.4659.1000')&lt;0 and ($n3424163Crash85950190501&gt;0)" Error="Error" P0="$n3424163Crash85950190501" Title="Known crashing issue when Outlook 2013 crashes opening certain email messages" Text="The crashing issue that is documented in KB 2889951 has been detected {0} time(s). To resolve this problem, please click the 'Click here...' link below and then install the x64 version of the hotfix provided in the article." GUID="517526" SSID="e657bda8-5deb-46d2-922c-3d14ad1df48a" Symptoms="Crash"></Rule>
      <Rule Name="s3424163CrashC2R" Query="$nInstallType='ClickToRun' and $n2DigitVersion=15 and versioncompare($sEmsmdb322013Version,'15.0.4659.1000')&lt;0 and ($n3424163Crash228059666&gt;0 or $n3424163Crash85950190501&gt;0)" Error="Error" P0="$n3424163Crash228059666 + $n3424163Crash85950190501" Title="Known crashing issue when Outlook 2013 crashes opening certain email messages" Text="The crashing issue that is documented in KB 2889881 has been detected {0} time(s). To resolve this problem, please click the 'Click here...' link below and then follow the instructions provided in the article to update your Office installation." GUID="517526" SSID="fcfc36b7-0024-4508-b96c-1a2b6080a695" Symptoms="Crash"></Rule>

      <Rule Name="n3487089Crash15x86" Query="count(../Instance[Setting[@Key1='Faulting Module Version' and ((Value='15.0.4667.1001') or (Value='0.0.0.0'))] and Setting[@Key1='Fault offset' and (lower-case(Value)='010eb9a9')] and Setting[@Key1='Faulting Module Name' and (lower-case(Value)='mso.dll')]])"></Rule>
      <Rule Name="s3487089Crash15x86MSI" Query="$nInstallType='MSI' and $n2DigitVersion=15 and $bitness='x86' and $n3487089Crash15x86&gt;0" Error="Error" P0="$n3487089Crash15x86" Title="Known crashing issue when Outlook 2013 is synchronizing an iCloud Internet calendar" Text="The crashing issue that is documented in KB 3019219 has been detected {0} time(s). To see information on how to resolve this problem, please click the 'Click here...' link below." GUID="519328" SSID="80ea26e3-ef22-466d-972d-b65e52c1f74e" Symptoms="Crash"></Rule>
      <Rule Name="s3487089Crash15x86C2R" Query="$nInstallType='ClickToRun' and $n2DigitVersion=15 and $n3487089Crash15x86&gt;0" Error="Error" P0="$n3487089Crash15x86" Title="Known crashing issue when Outlook 2013 is synchronizing an iCloud Internet calendar" Text="The crashing issue that is documented in KB 3019219 has been detected {0} time(s). To see information on how to resolve this problem, please click the 'Click here...' link below." GUID="519328" SSID="70cfa69a-5df6-4c7e-9bba-9a234f2bf0b5" Symptoms="Crash"></Rule>

      <Rule Name="n3487089Crash14" Query="count(../Instance[Setting[@Key1='Faulting Module Version' and ((Value='14.0.7128.5000') or (Value='0.0.0.0'))] and Setting[@Key1='Fault offset' and (lower-case(Value)='0070af37')] and Setting[@Key1='Faulting Module Name' and (lower-case(Value)='mso.dll')]])"></Rule>
      <Rule Name="s3487089Crash14" Query="$n2DigitVersion=14 and $n3487089Crash14&gt;0" Error="Error" P0="$n3487089Crash14" Title="Known crashing issue when Outlook 2010 is synchronizing an iCloud Internet calendar" Text="The crashing issue that is documented in KB 3019219 has been detected {0} time(s). To see information on how to resolve this problem, please click the 'Click here...' link below." GUID="519328" SSID="6fe2a99f-7498-4467-8f4e-f911e7e22fc7" Symptoms="Crash"></Rule>

      <Rule Name="n3443643Crash_234668874" Query="count(../Instance[Setting[@Key1='Faulting Module Version' and (Value='6.3.9600.16408')] and Setting[@Key1='Fault offset' and (lower-case(Value)='0001e12c')] and Setting[@Key1='Faulting Module Name' and (lower-case(Value)='ntdll.dll')]])"></Rule>
      <Rule Name="n3443643Crash73316690690" Query="count(../Instance[Setting[@Key1='Faulting Module Version' and (Value='6.3.9600.17114')] and Setting[@Key1='Fault offset' and (lower-case(Value)='0001ec81')] and Setting[@Key1='Faulting Module Name' and (lower-case(Value)='ntdll.dll')]])"></Rule>
      <Rule Name="n3443643Crash73451700550" Query="count(../Instance[Setting[@Key1='Faulting Module Version' and (Value='6.2.9200.17046')] and Setting[@Key1='Fault offset' and (lower-case(Value)='00023e30')] and Setting[@Key1='Faulting Module Name' and (lower-case(Value)='ntdll.dll')]])"></Rule>
      <Rule Name="n3443643Crash73330822095" Query="count(../Instance[Setting[@Key1='Faulting Module Version' and (Value='6.2.9200.16912')] and Setting[@Key1='Fault offset' and (lower-case(Value)='00023e60')] and Setting[@Key1='Faulting Module Name' and (lower-case(Value)='ntdll.dll')]])"></Rule>
      <Rule Name="n3443643Crash73109858506" Query="count(../Instance[Setting[@Key1='Faulting Module Version' and (Value='6.3.9600.17031')] and Setting[@Key1='Fault offset' and (lower-case(Value)='0001f0a3')] and Setting[@Key1='Faulting Module Name' and (lower-case(Value)='ntdll.dll')]])"></Rule>
      <Rule Name="n3443643Crash73508397964" Query="count(../Instance[Setting[@Key1='Faulting Module Version' and (Value='6.3.9600.17278')] and Setting[@Key1='Fault offset' and (lower-case(Value)='0001d4f1')] and Setting[@Key1='Faulting Module Name' and (lower-case(Value)='ntdll.dll')]])"></Rule>
      <Rule Name="s3443643CrashMSIx86" Query="$nInstallType='MSI' and $bitness='x86' and versioncompare($sFullAppVersion,'15.0.4659.1000')&lt;0 and ($n3443643Crash_234668874&gt;0 or $n3443643Crash73316690690&gt;0 or $n3443643Crash73451700550&gt;0 or $n3443643Crash73330822095&gt;0 or $n3443643Crash73109858506&gt;0 or $n3443643Crash73508397964&gt;0)" Error="Error" P0="$n3443643Crash_234668874 + $n3443643Crash73316690690 + $n3443643Crash73451700550 + $n3443643Crash73330822095 + $n3443643Crash73109858506 + $n3443643Crash73508397964" Title="Known crashing issue that occurs when you exit Outlook" Text="The crashing issue that is documented in KB 2889951 has been detected {0} time(s). To resolve this problem, please click the 'Click here...' link below and then install the 32-bit (x86) hotfix provided in the article. Or, install the latest update for Outlook 2013 using the information provided in KB article 2625547." GUID="517530" SSID="82aee9b4-72d5-4227-b24a-ab1b0aff7c9f" Symptoms="Crash"></Rule>

      <Rule Name="n3443643Crash85957145446" Query="count(../Instance[Setting[@Key1='Faulting Module Version' and (Value='6.3.9600.17278')] and Setting[@Key1='Fault offset' and (lower-case(Value)='0000000000039a7a')] and Setting[@Key1='Faulting Module Name' and (lower-case(Value)='ntdll.dll')]])"></Rule>
      <Rule Name="n3443643Crash85958471435" Query="count(../Instance[Setting[@Key1='Faulting Module Version' and (Value='6.2.9200.16912')] and Setting[@Key1='Fault offset' and (lower-case(Value)='00000000000413e0')] and Setting[@Key1='Faulting Module Name' and (lower-case(Value)='ntdll.dll')]])"></Rule>
      <Rule Name="n3443643Crash85925820787" Query="count(../Instance[Setting[@Key1='Faulting Module Version' and (Value='6.3.9600.17031')] and Setting[@Key1='Fault offset' and (lower-case(Value)='0000000000065e8e')] and Setting[@Key1='Faulting Module Name' and (lower-case(Value)='ntdll.dll')]])"></Rule>
      <Rule Name="n3443643Crash85941103880" Query="count(../Instance[Setting[@Key1='Faulting Module Version' and (Value='6.3.9600.17114')] and Setting[@Key1='Fault offset' and (lower-case(Value)='000000000006361a')] and Setting[@Key1='Faulting Module Name' and (lower-case(Value)='ntdll.dll')]])"></Rule>
      <Rule Name="s3443643CrashMSIx64" Query="$nInstallType='MSI' and $bitness='x64' and versioncompare($sFullAppVersion,'15.0.4659.1000')&lt;0 and ($n3443643Crash85957145446&gt;0 or $n3443643Crash85958471435&gt;0 or $n3443643Crash85925820787&gt;0 or $n3443643Crash85941103880&gt;0)" Error="Error" P0="$n3443643Crash85957145446 + $n3443643Crash85958471435 + $n3443643Crash85925820787 + $n3443643Crash85941103880" Title="Known crashing issue that occurs when you exit Outlook" Text="The crashing issue that is documented in KB 2889951 has been detected {0} time(s). To resolve this problem, please click the 'Click here...' link below and then install the 64-bit (x64) hotfix provided in the article. Or, install the latest update for Outlook 2013 using the information provided in KB article 2625547." GUID="517530" SSID="88da5103-2aa8-460c-9c80-5cd2a4f719bc" Symptoms="Crash"></Rule>

      <Rule Name="s3443643CrashC2R" Query="$nInstallType='ClickToRun' and versioncompare($C2R_Updates_fInstalledC2RVersion,'15.0.4659.1001')&lt;0 and ($n3443643Crash_234668874&gt;0 or $n3443643Crash73316690690&gt;0 or $n3443643Crash73451700550&gt;0 or $n3443643Crash73330822095&gt;0 or $n3443643Crash73109858506&gt;0 or $n3443643Crash73508397964&gt;0)" Error="Error" P0="$n3443643Crash_234668874 + $n3443643Crash73316690690 + $n3443643Crash73451700550 + $n3443643Crash73330822095 + $n3443643Crash73109858506 + $n3443643Crash73508397964" Title="Known crashing issue that occurs when you exit Outlook" Text="The crashing issue that is documented in KB 2889951 has been detected {0} time(s). To resolve this problem, please click the 'Click here...' link below and then follow the instructions provided in the article to update your Office installation." GUID="517532" SSID="b63b2b79-12a1-4fc9-8a3c-6146d2c982ee" Symptoms="Crash"></Rule>

    </Object>

    <Reference Type="DisplayLinkUMD" Name="DisplayLinkUMD" File="common.config.xml">
    </Reference>

  </Type>

  <Reference Type="OutlookCrashes" Name="OutlookCrashes" File="outlook.crashes.config.xml">
  </Reference>
  <Reference Type="MSO" Name="MSO" File="common.config.xml">
  </Reference>
  <Reference Type="C2R_Updates" Name="C2R_Updates" File="common.config.xml">
  </Reference>
  <Reference Type="Office_Updates" Name="OfficeUpdates" File="officeupdates.config.xml">
  </Reference>

  <!--EXTERNALREFS-->
	<Rule Name="sPpCoreVersion"></Rule>
  <Rule Name="sWordVersion"></Rule>

<Signature xmlns="http://www.w3.org/2000/09/xmldsig#"><SignedInfo><CanonicalizationMethod Algorithm="http://www.w3.org/TR/2001/REC-xml-c14n-20010315"/><SignatureMethod Algorithm="http://www.w3.org/2000/09/xmldsig#rsa-sha1"/><Reference URI=""><Transforms><Transform Algorithm="http://www.w3.org/2000/09/xmldsig#enveloped-signature"/><Transform Algorithm="http://www.w3.org/TR/2001/REC-xml-c14n-20010315"/></Transforms><DigestMethod Algorithm="http://www.w3.org/2000/09/xmldsig#sha1"/><DigestValue>BpM6CIdtzTL6Eof5T0zHq4vmzY8=</DigestValue></Reference></SignedInfo><SignatureValue>
    gDDxZkxidIRBD0OifssLI2qrpa6QkKxyyVhavpvwg2nDPTFHZf/FrIi2P/3qYTUvOvzJO7QE
    LognqE873G18XMzbjJ9B1YviCO68Eyj2ZGz3opdhcCp+NdSO/0FWM2veaymRHdVZur1ZyWMM
    JLetC3+zOCwjgWPF/FVTu1ZaxSLcIpzJ9waM6FAydT7PZK6SCNvES+KxaU7vFZs7pvN861Ck
    ML9k6rp9cfESaVjiW5zPrMbYDeRk+owPWt3SZScHCpIik9TDNhXN5hfR/rUbiVEtfacBtqPF
    jk5+y+7n9HvrpYtxMEF6J4CZ79wevOOQn7XcSjA7WgXNzjsnkm1iWw==
  </SignatureValue><KeyInfo>
      <KeyValue>
        <RSAKeyValue>
          <Modulus>
            lnFd7QZG+oTLnVu3Rsew4bQROQOtsRVzYJzrp7ZuGjw//2XjNPGmpSFeVplsWOSSoQpcwtPc
            Ui8MZZogYUBTMZxsjyF9uvn+E1BSYJU6W7lYpXRhQamU4K0mTkyhl3BJJ158Z8pPHnGERrwd
            S7biD8XGJ8kH5noKpRcAGUxwRTgtgbRQqsVn0fp5vMXMoXKb9CU0mPhU3xI5OBIvpGulmn7H
            YtHcz+09NPi53zUwuux5MqnhqaxVTUx/TFbDEwt28Qf5zEes+4jVUqUeKPo9Lc/PhJiGcWUR
            z4XJCUSG4W/nsfysQESlqYsjP4JJndWWWVATWRhz/0MMrSvUfzBAZw==
          </Modulus>
          <Exponent>AQAB</Exponent>
        </RSAKeyValue>
      </KeyValue>
      <X509Data>
        <X509Certificate>
          MIIE7DCCA9SgAwIBAgITMwAAAMps1TISNcThVQABAAAAyjANBgkqhkiG9w0BAQUFADB5MQsw
          CQYDVQQGEwJVUzETMBEGA1UECBMKV2FzaGluZ3RvbjEQMA4GA1UEBxMHUmVkbW9uZDEeMBwG
          A1UEChMVTWljcm9zb2Z0IENvcnBvcmF0aW9uMSMwIQYDVQQDExpNaWNyb3NvZnQgQ29kZSBT
          aWduaW5nIFBDQTAeFw0xNDA0MjIxNzM5MDBaFw0xNTA3MjIxNzM5MDBaMIGDMQswCQYDVQQG
          EwJVUzETMBEGA1UECBMKV2FzaGluZ3RvbjEQMA4GA1UEBxMHUmVkbW9uZDEeMBwGA1UEChMV
          TWljcm9zb2Z0IENvcnBvcmF0aW9uMQ0wCwYDVQQLEwRNT1BSMR4wHAYDVQQDExVNaWNyb3Nv
          ZnQgQ29ycG9yYXRpb24wggEiMA0GCSqGSIb3DQEBAQUAA4IBDwAwggEKAoIBAQCWcV3tBkb6
          hMudW7dGx7DhtBE5A62xFXNgnOuntm4aPD//ZeM08aalIV5WmWxY5JKhClzC09xSLwxlmiBh
          QFMxnGyPIX26+f4TUFJglTpbuVildGFBqZTgrSZOTKGXcEknXnxnyk8ecYRGvB1LtuIPxcYn
          yQfmegqlFwAZTHBFOC2BtFCqxWfR+nm8xcyhcpv0JTSY+FTfEjk4Ei+ka6Wafsdi0dzP7T00
          +LnfNTC67HkyqeGprFVNTH9MVsMTC3bxB/nMR6z7iNVSpR4o+j0tz8+EmIZxZRHPhckJRIbh
          b+ex/KxARKWpiyM/gkmd1ZZZUBNZGHP/QwytK9R/MEBnAgMBAAGjggFgMIIBXDATBgNVHSUE
          DDAKBggrBgEFBQcDAzAdBgNVHQ4EFgQUH17iXVCNVoa+SjzPBOinh7XLv4MwUQYDVR0RBEow
          SKRGMEQxDTALBgNVBAsTBE1PUFIxMzAxBgNVBAUTKjMxNTk1K2I0MjE4ZjEzLTZmY2EtNDkw
          Zi05YzQ3LTNmYzU1N2RmYzQ0MDAfBgNVHSMEGDAWgBTLEejK0rQWWAHJNy4zFha5TJoKHzBW
          BgNVHR8ETzBNMEugSaBHhkVodHRwOi8vY3JsLm1pY3Jvc29mdC5jb20vcGtpL2NybC9wcm9k
          dWN0cy9NaWNDb2RTaWdQQ0FfMDgtMzEtMjAxMC5jcmwwWgYIKwYBBQUHAQEETjBMMEoGCCsG
          AQUFBzAChj5odHRwOi8vd3d3Lm1pY3Jvc29mdC5jb20vcGtpL2NlcnRzL01pY0NvZFNpZ1BD
          QV8wOC0zMS0yMDEwLmNydDANBgkqhkiG9w0BAQUFAAOCAQEAd1zr15E9zb17g9mFqbBDnXN8
          F8kP7Tbbx7UsG177VAU6g3FAgQmit3EmXtZ9tmw7yapfXQMYKh0nfgfpxWUftc8Nt1THKDha
          iOd7wRm2VjK64szLk9uvbg9dRPXUsO8b1U7Brw7vIJvy4f4nXejF/2H2GdIoCiKd381wgp4Y
          ctgjzHosQ+7/6sDg5h2qnpczAFJvB7jTiGzepAY1p8JThmURdwmPNVm52IaoAP74MX0s9IwF
          ncDB1XdybOlNWSaD8cKyiFeTNQB8UCu8Wfz+HCk4gtPeUpdFKRhOlludul8bo/EnUOoHleht
          NA04V9w3KDWVOjic1O1qhV0OIhFeew==
        </X509Certificate>
      </X509Data>
      <X509Data>
        <X509Certificate>
          MIIFmTCCA4GgAwIBAgIQea0WoUqgpa1Mc1j0BxMuZTANBgkqhkiG9w0BAQUFADBfMRMwEQYK
          CZImiZPyLGQBGRYDY29tMRkwFwYKCZImiZPyLGQBGRYJbWljcm9zb2Z0MS0wKwYDVQQDEyRN
          aWNyb3NvZnQgUm9vdCBDZXJ0aWZpY2F0ZSBBdXRob3JpdHkwHhcNMDEwNTA5MjMxOTIyWhcN
          MjEwNTA5MjMyODEzWjBfMRMwEQYKCZImiZPyLGQBGRYDY29tMRkwFwYKCZImiZPyLGQBGRYJ
          bWljcm9zb2Z0MS0wKwYDVQQDEyRNaWNyb3NvZnQgUm9vdCBDZXJ0aWZpY2F0ZSBBdXRob3Jp
          dHkwggIiMA0GCSqGSIb3DQEBAQUAA4ICDwAwggIKAoICAQDzXfqAZ9Rap6kMLJAg0DUIPHWE
          zbcHiZyJ2t7Ow2D6kWhanpRxKRh2fMLgyCV2lA5Y+gQ0Nubfr/eAuulYCyuT5Z0F43cikfc0
          ZDwikR1e4QmQvBT+/HVYGeF5tweSo66IWQjYnwfKA1j8aCltMtfSqMtL/OELSDJP5uu4rU/k
          XG8TlJnbldV126gat5SRtHdb9UgMj2p5fRRwBH1tr5D12nDYR7e/my9s5wW34RFgrHmRFHzF
          1qbk4X7Vw37lktI8ALU2gt554W3ztW74nzPJy1J9c5g224uha6KVl5uj3sJNJv8GlmclBsjn
          rOTuEjOVMZnINQhONMp5U9W1vmMyWUA2wKVOBE0921sHM+RYv+8/U2TYQlk1V/0PRXwkBE2e
          1jh0EZcikM5oRHSSb9VLb7CG48c2QqDQ/MHAWvmjYbkwR3GWChawkcBCle8Qfyhq4yofseTN
          Az93cQTHIPxJDx1FiKTXy36IrY4t7EXbxFEEySr87IaemhGXW97OU4jm4rf9rJXCKEDb7wSQ
          34EzOdmyRaUjhwalVYkxuwYtYA5BGH0fLrWXyxHrFdUkpZTvFRSJ/Utz+jJb/NEzAPlZYnAH
          Muouq0Ate8rdIWcbMJmPFqojqEHRsG4RmzbE3kB0nOFYZcFgHnpbOMiPuwQmfNQWQOW2a2yq
          hv0Av87BNQIDAQABo1EwTzALBgNVHQ8EBAMCAcYwDwYDVR0TAQH/BAUwAwEB/zAdBgNVHQ4E
          FgQUDqyCYEBWJ5flJRP8KuEKU5VZ5KQwEAYJKwYBBAGCNxUBBAMCAQAwDQYJKoZIhvcNAQEF
          BQADggIBAMURTQM6YN1dUhF3j7K7NsiyBb+0t6jYIJ1cEwO2HCL6BhM1tshj1JpHbyZX0lXx
          BLEmX9apUGigvNK4bszD6azfGc14rFl0rGY0NsQbPmw4TDMOMBINoyb+UVMA/69aToQNDx/k
          bQUuToVLjWwzb1TSZKu/UK99ejmgN+1jAw/8EwbOFjbUVDuVG1FiOuVNF9QFOZKaJ6hbqr3s
          u77jIIlgcWxWs6UT0G0OI36VA+1oPfLYY7hrTbboMLXhypRL96KqXZkwsj2nwlFsKCABJCcr
          SwC3nRFrcL6yEIK8DJto0I07JIeqmShynTNfWZC99d6TnjpiWjQ54ohVHbkGsMGJay3XacMZ
          EjaE0Mmg2v8vaXiy5Xra69cMwPe9Yxe4ORM4ojZbe/KFVmodZGLBOOKqv1FmopT1EpxmIhBr
          8rcwki3yKfA9OxRDaKLxnCk3y844ICVtfGfzfiQSJAMIgUfspZ6X9RjXz7vV73aW7/3O21ad
          laBC+ZdY4dcxItNfWeY+biIA6kOEtiXb2fMIVmjAZGsdfOy2k6JiV24u2OdYj8QxSSbd3ik1
          h/UwcXBbFDxpvYkSfesuo/7Yf56CWlIKK8FDK9kwiJ/IEPuJjeahhXUzfmye23MTZGJppS99
          ypZtn/gETTCSPW4hFCHJPeDD/YprnUr90aGdmUN3P7Da
        </X509Certificate>
      </X509Data>
      <X509Data>
        <X509Certificate>
          MIIFvDCCA6SgAwIBAgIKYTMmGgAAAAAAMTANBgkqhkiG9w0BAQUFADBfMRMwEQYKCZImiZPy
          LGQBGRYDY29tMRkwFwYKCZImiZPyLGQBGRYJbWljcm9zb2Z0MS0wKwYDVQQDEyRNaWNyb3Nv
          ZnQgUm9vdCBDZXJ0aWZpY2F0ZSBBdXRob3JpdHkwHhcNMTAwODMxMjIxOTMyWhcNMjAwODMx
          MjIyOTMyWjB5MQswCQYDVQQGEwJVUzETMBEGA1UECBMKV2FzaGluZ3RvbjEQMA4GA1UEBxMH
          UmVkbW9uZDEeMBwGA1UEChMVTWljcm9zb2Z0IENvcnBvcmF0aW9uMSMwIQYDVQQDExpNaWNy
          b3NvZnQgQ29kZSBTaWduaW5nIFBDQTCCASIwDQYJKoZIhvcNAQEBBQADggEPADCCAQoCggEB
          ALJyWVwZMGS/HZpgICBCmXZTbD4b1m/My/Hqa/6XFhDg3zp0gxq3L6Ay7P/ewkJOI9VyANs1
          VwqJyq4gSfTwaKxNS42lvXlLcZtHB9r9Jd+ddYjPqnNEf9eB2/O98jakyVxF3K+tPeAoaJca
          p6Vyc1bxF5Tk/TWUcqDWdl8ed0WDhTgW0HNbBbpnUo2lsmkv2hkL/pJ0KeJ2L1TdFDBZ+NKN
          Yv3LyV9GMVC5JxPkQDDPcikQKCLHN049oDI9kM2hOAaFXE5WgigqBTK3S9dPY+fSLWLxRT3n
          rAgA9kahntFbjCZT6HqqSvJGzzc8OJ60d1ylF56NyxGPVjzBrAlfA9MCAwEAAaOCAV4wggFa
          MA8GA1UdEwEB/wQFMAMBAf8wHQYDVR0OBBYEFMsR6MrStBZYAck3LjMWFrlMmgofMAsGA1Ud
          DwQEAwIBhjASBgkrBgEEAYI3FQEEBQIDAQABMCMGCSsGAQQBgjcVAgQWBBT90TFO0yaKleGY
          YDuoMW+mPLzYLTAZBgkrBgEEAYI3FAIEDB4KAFMAdQBiAEMAQTAfBgNVHSMEGDAWgBQOrIJg
          QFYnl+UlE/wq4QpTlVnkpDBQBgNVHR8ESTBHMEWgQ6BBhj9odHRwOi8vY3JsLm1pY3Jvc29m
          dC5jb20vcGtpL2NybC9wcm9kdWN0cy9taWNyb3NvZnRyb290Y2VydC5jcmwwVAYIKwYBBQUH
          AQEESDBGMEQGCCsGAQUFBzAChjhodHRwOi8vd3d3Lm1pY3Jvc29mdC5jb20vcGtpL2NlcnRz
          L01pY3Jvc29mdFJvb3RDZXJ0LmNydDANBgkqhkiG9w0BAQUFAAOCAgEAWTk+fyZGr+tvQLEy
          tWrrDi9uqEn361917Uw7LddDrQv+y+ktMaMjzHxQmIAhXaw9L0y6oqhWnONwu7i0+Hm1SXL3
          PupBf8rhDBdpy6WcIC36C1DEVs0t40rSvHDnqA2iA6VW4LiKS1fylUKc8fPv7uOGHzQ8uFaa
          8FMjhSqkghyT4pQHHfLiTviMocroE6WRTsgb0o9ylSpxbZsa+BzwU9ZnzCL/XB3Nooy9J7J5
          Y1ZEolHN+emjWFbdmwJFRC9f9Nqu1IIybvyklRPk62nnqaIsvsgrEA5ljpnb9aL6EiYJZTiU
          8XofSrvR4Vbo0HiWGFzJNRZf3ZMdSY4tvq00RBzuEBUaAF3dNVshzpjHCe6FDoxPbQ4TTj18
          KUicctHzbMrB7HCjV5JXfZSNoBtIA1r3z6NnCnSlNu0tLxfI5nI3EvRvsTxngvlSso0zFmUe
          DordEN5k9G/ORtTTF+l5xAS00/ss3x+KnqwK+xMnQK3k+eGpf0a7B2BHZWBATrBC7E7ts3Z5
          2Ao0CW0cgDEf4g5U3eWh++VHEK1kmP9QFi58vwUheuKVQSdpw5OPlcmN2Jshrg1cnPCiroZo
          gwxqLbt2awAdlq3yFnv2FoMkuYjPaqhHMS+a3ONxPdcAfmJH0c6IybgY+g5yjcGjPa8CQGr/
          aZuW4hCoELQ3UAjWwz0=
        </X509Certificate>
      </X509Data>
    </KeyInfo><Object id="ts-countersig"><X509Data><X509Certificate>MIIEuzCCA6OgAwIBAgITMwAAAF3JyvZpIzdoUAAAAAAAXTANBgkqhkiG9w0BAQUFADB3MQswCQYD
VQQGEwJVUzETMBEGA1UECBMKV2FzaGluZ3RvbjEQMA4GA1UEBxMHUmVkbW9uZDEeMBwGA1UEChMV
TWljcm9zb2Z0IENvcnBvcmF0aW9uMSEwHwYDVQQDExhNaWNyb3NvZnQgVGltZS1TdGFtcCBQQ0Ew
HhcNMTQwNTIzMTcxMzE3WhcNMTUwODIzMTcxMzE3WjCBqzELMAkGA1UEBhMCVVMxCzAJBgNVBAgT
AldBMRAwDgYDVQQHEwdSZWRtb25kMR4wHAYDVQQKExVNaWNyb3NvZnQgQ29ycG9yYXRpb24xDTAL
BgNVBAsTBE1PUFIxJzAlBgNVBAsTHm5DaXBoZXIgRFNFIEVTTjo3RDJFLTM3ODItQjBGNzElMCMG
A1UEAxMcTWljcm9zb2Z0IFRpbWUtU3RhbXAgU2VydmljZTCCASIwDQYJKoZIhvcNAQEBBQADggEP
ADCCAQoCggEBAKu6ei+vVB909A1zsuALhVjsq6u/RwD+jTcx8hyTPqa6zhvmUUBo1IAY11hjXQM3
NvuDWHDexDM2sF8Hf33991irWpduRc648Rs9Us+lPQVDm6CxNHLT7/MxvC5ojio1Cy50sO/kK1Vy
ZZWPZ/SjyO8DEafcCzyhbA7/YYxCkuRWw5Gxj/au18Hj6KgZAaIXYL9DmHoqWmo0yJINP+BcHbd/
sFodvcxsahFDHgINW0LpbUtjCzn7UqPseibSojBHY9L46hXYaS6eJulOTxyz0uJgJj9uXZIUkF40
bXgEfFJRmwsBdutBAFlTztuN1kmFbII7fsTph0ayOTzxXthvcv8CAwEAAaOCAQkwggEFMB0GA1Ud
DgQWBBTXVOYV2dNdyiTVARjweGSZe2hMMzAfBgNVHSMEGDAWgBQjNPjZUkZwCu1A+3b7syuwwzWz
DzBUBgNVHR8ETTBLMEmgR6BFhkNodHRwOi8vY3JsLm1pY3Jvc29mdC5jb20vcGtpL2NybC9wcm9k
dWN0cy9NaWNyb3NvZnRUaW1lU3RhbXBQQ0EuY3JsMFgGCCsGAQUFBwEBBEwwSjBIBggrBgEFBQcw
AoY8aHR0cDovL3d3dy5taWNyb3NvZnQuY29tL3BraS9jZXJ0cy9NaWNyb3NvZnRUaW1lU3RhbXBQ
Q0EuY3J0MBMGA1UdJQQMMAoGCCsGAQUFBwMIMA0GCSqGSIb3DQEBBQUAA4IBAQCJMKxtI1M8/5xe
n1dwDBzeF903pNyVsaYkzAfuqYXRHNXZm0k3IZ8xPmmuv7UwG+ekLFDrwVCISqq17KiyCUCwau9z
VEKtnimFVG2zD/GYfuP4wDAbTNKGKfCi5V6bN41mnei8W2+6lcb20i5BNfnHvgyK5iZEdmgcnKQW
7iJVpNZXK/gNgSAsoQ+ajvzHlcVeh4RB4tJvnM/QZSMW29B9hNAGFhKlZy17hYk+RZPYzSaZ+7Yq
4VJCmhCXHzTakcGshvOSRG1Qu4mykew1qEj2weHE/sZlfUHv7W3KkeTmsNnlWFy0u5romkYcZt0e
S0SYyfRKWBF/kMshN4hDyN71</X509Certificate></X509Data><X509Data><X509Certificate>MIIGBzCCA++gAwIBAgIKYRZoNAAAAAAAHDANBgkqhkiG9w0BAQUFADBfMRMwEQYKCZImiZPyLGQB
GRYDY29tMRkwFwYKCZImiZPyLGQBGRYJbWljcm9zb2Z0MS0wKwYDVQQDEyRNaWNyb3NvZnQgUm9v
dCBDZXJ0aWZpY2F0ZSBBdXRob3JpdHkwHhcNMDcwNDAzMTI1MzA5WhcNMjEwNDAzMTMwMzA5WjB3
MQswCQYDVQQGEwJVUzETMBEGA1UECBMKV2FzaGluZ3RvbjEQMA4GA1UEBxMHUmVkbW9uZDEeMBwG
A1UEChMVTWljcm9zb2Z0IENvcnBvcmF0aW9uMSEwHwYDVQQDExhNaWNyb3NvZnQgVGltZS1TdGFt
cCBQQ0EwggEiMA0GCSqGSIb3DQEBAQUAA4IBDwAwggEKAoIBAQCfoWyx39tIkip8ay4Z4b3i48WZ
USNQrc7dGE4kD+7Rp9FMrXQwIBHrB9VUlRVJlBtCkq6YXDAm2gBr6Hu97IkHD/cOBJjwicwfyzMk
h53y9GccLPx754gd6udOo6HBI1PKjfpFzwnQXq/QsEIEovmmbJNn1yjcRlOwhtDlKEYuJ6yGT1VS
DOQDLPtqkJAwbofzWTCd+n7Wl7PoIZd++NIT8wi3U21StEWQn0gASkdmEScpZqiX5NMGgUqi+YSn
EUcUCYKfhO1VeP4Bmh1QCIUAEDBG7bfeI0a7xC1Un68eeEExd8yb3zuDk6FhArUdDbH895uyAc4i
S1T/+QXDwiALAgMBAAGjggGrMIIBpzAPBgNVHRMBAf8EBTADAQH/MB0GA1UdDgQWBBQjNPjZUkZw
Cu1A+3b7syuwwzWzDzALBgNVHQ8EBAMCAYYwEAYJKwYBBAGCNxUBBAMCAQAwgZgGA1UdIwSBkDCB
jYAUDqyCYEBWJ5flJRP8KuEKU5VZ5KShY6RhMF8xEzARBgoJkiaJk/IsZAEZFgNjb20xGTAXBgoJ
kiaJk/IsZAEZFgltaWNyb3NvZnQxLTArBgNVBAMTJE1pY3Jvc29mdCBSb290IENlcnRpZmljYXRl
IEF1dGhvcml0eYIQea0WoUqgpa1Mc1j0BxMuZTBQBgNVHR8ESTBHMEWgQ6BBhj9odHRwOi8vY3Js
Lm1pY3Jvc29mdC5jb20vcGtpL2NybC9wcm9kdWN0cy9taWNyb3NvZnRyb290Y2VydC5jcmwwVAYI
KwYBBQUHAQEESDBGMEQGCCsGAQUFBzAChjhodHRwOi8vd3d3Lm1pY3Jvc29mdC5jb20vcGtpL2Nl
cnRzL01pY3Jvc29mdFJvb3RDZXJ0LmNydDATBgNVHSUEDDAKBggrBgEFBQcDCDANBgkqhkiG9w0B
AQUFAAOCAgEAEJeKw1wDRDbd6bStd9vOeVFNAbEudHFbbQwTq86+e4+4LtQSooxtYrhXAstOIBNQ
md16QOJXu69YmhzhHQGGrLt48ovQ7DsB7uK+jwoFyI1I4vBTFd1Pq5Lk541q1YDB5pTyBi+FA+mR
KiQicPv2/OR4mS4N9wficLwYTp2OawpylbihOZxnLcVRDupiXD8WmIsgP+IHGjL5zDFKdjE9K3IL
yOpwPf+FChPfwgphjvDXuBfrTot/xTUrXqO/67x9C0J71FNyIe4wyrt4ZVxbARcKFA7S2hSY9Ty5
ZlizLS/n+YWGzFFW6J1wlGysOUzU9nm/qhh6YinvopspNAZ3GmLJPR5tH4LwC8csu89Ds+X57H21
46SodDW4TsVxIxImdgs8UoxxWkZDFLyzs7BNZ8ifQv+AeSGAnhUwZuhCEl4ayJ4iIdBD6Svpu/RI
zCzU2DKATCYqSCRfWupW76bemZ3KOm+9gSd0BhHudiG/m4LBJ1S2sWo9iaF2YbRuoROmv6pH8BJv
/YoybLL+31HIjCPJZr2dHYcSZAI9La9Zj7jkIeW1sMpjtHhUBdRBLlCslLCleKuzoJZ1GtmShxN1
Ii8yqAhuoFuMJb+g74TKIdbrHk/Jmu5J4PcBZW+JC33Iacjmbuqnl84xKf8OxVtc2E0bodj6L54/
LlUWa8kTo/0=</X509Certificate></X509Data><CounterSignature xmlns="http://schemas.microsoft.com/xmldsig/timestamp/2003" ts-format="cms-timestamp-message">MIIGzAYJKoZIhvcNAQcCoIIGvTCCBrkCAQMxCzAJBgUrDgMCGgUAMIIBEwYJKoZIhvcNAQcBoIIB
BASCAQCAMPFmTGJ0hEEPQ6J+ywsjaqulrpCQrHLJWFq+m/CDacM9MUdl/8WsiLY//ephNS86/Mk7
tAQuiCeoTzvcbXxczNuMn0HVi+II7rwTKPZkbPeil2FwKn411I7/QVYza95rKZEd1Vm6vVnJYwwk
t60Lf7M4LCOBY8X8VVO7VlrFItwinMn3BozoUDJ1Ps9krpII28RL4rFpTu8Vmzum83zrUKQwv2Tq
un1x8RJpWOJbnM+sxtgN5GT6jA9a3dJlJwcKkiKT1MM2Fc3mF9H+tRuJUS19pwG2o8WOTn7L7uf0
e+uli3EwQXongJnv3B6845CftdxKMDtaBc3OOyeSbWJboIIDdaGCA3EwggJZAgEBMIHboYGxpIGu
MIGrMQswCQYDVQQGEwJVUzELMAkGA1UECBMCV0ExEDAOBgNVBAcTB1JlZG1vbmQxHjAcBgNVBAoT
FU1pY3Jvc29mdCBDb3Jwb3JhdGlvbjENMAsGA1UECxMETU9QUjEnMCUGA1UECxMebkNpcGhlciBE
U0UgRVNOOjdEMkUtMzc4Mi1CMEY3MSUwIwYDVQQDExxNaWNyb3NvZnQgVGltZS1TdGFtcCBTZXJ2
aWNloiUKAQEwCQYFKw4DAhoFAAMVADGQj3DCILvjoZE/7XwqqDC1ZVQ1oIHCMIG/pIG8MIG5MQsw
CQYDVQQGEwJVUzETMBEGA1UECBMKV2FzaGluZ3RvbjEQMA4GA1UEBxMHUmVkbW9uZDEeMBwGA1UE
ChMVTWljcm9zb2Z0IENvcnBvcmF0aW9uMQ0wCwYDVQQLEwRNT1BSMScwJQYDVQQLEx5uQ2lwaGVy
IE5UUyBFU046NTdGNi1DMUUwLTU1NEMxKzApBgNVBAMTIk1pY3Jvc29mdCBUaW1lIFNvdXJjZSBN
YXN0ZXIgQ2xvY2swDQYJKoZIhvcNAQEFBQACBQDYHTrHMCIYDzIwMTQxMTI0MDUwNDA3WhgPMjAx
NDExMjUwNTA0MDdaMHcwPQYKKwYBBAGEWQoEATEvMC0wCgIFANgdOscCAQAwCgIBAAICDBQCAf8w
BwIBAAICGvIwCgIFANgejEcCAQAwNgYKKwYBBAGEWQoEAjEoMCYwDAYKKwYBBAGEWQoDAaAKMAgC
AQACAxbjYKEKMAgCAQACAwehIDANBgkqhkiG9w0BAQUFAAOCAQEAb+MSzYT8XwHg1ZCWjnDcZW2j
YEf+kzLbfEh3ESlzM8Ct60XRWOp4+XmFZ8myV3soPqwHZRQRsBs6gK66SykZNw3qeq0ohYkyMP59
zVbyRoy4FBr+t7lBQRQItsurj7QLxSYk8jCXMmhr7TSqDr5/i4DI0Y1zXRAXcmdCStHJHlJKRfQz
eXDMptDFVYM6y1WNN6s2TGnKsGupbWVopG+Twp00rwdGEfBwmkrMoPp+Q6RVOQO2IPZ2x0EtCyyG
Q4WnQXu0ZpunCzCPD6zMQGFjv9swXIW5+AkcjX4nApN8177abLbfCLpmhgzU48Wkvuy8MKLatn2H
IIBal7X2x2RqcjGCAhUwggIRAgEBMIGOMHcxCzAJBgNVBAYTAlVTMRMwEQYDVQQIEwpXYXNoaW5n
dG9uMRAwDgYDVQQHEwdSZWRtb25kMR4wHAYDVQQKExVNaWNyb3NvZnQgQ29ycG9yYXRpb24xITAf
BgNVBAMTGE1pY3Jvc29mdCBUaW1lLVN0YW1wIFBDQQITMwAAAF3JyvZpIzdoUAAAAAAAXTAJBgUr
DgMCGgUAoF0wGAYJKoZIhvcNAQkDMQsGCSqGSIb3DQEHATAcBgkqhkiG9w0BCQUxDxcNMTQxMTI0
MTYwNjUyWjAjBgkqhkiG9w0BCQQxFgQUNA3JY+GvjyYfHQpjQubsgk6hDDgwDQYJKoZIhvcNAQEF
BQAEggEAbUn0r+1VkQghnWob1t0KD66qioLuKdt/vCQOX+Hv6vM0zCavzNvGecFRaIAv8boXC+CY
TwiEQoKz8EYJb71M4OiMR5fW9urH58S6ypzl6NM4N/m1GvZbAXlwYXOvi5nBlNmkTh4523DMGPJ3
9lNfZqkV5JK9NqCS7YQ8zIcaBaBzuWsSgokrh175DjfMy5CkMouBbLLtKvOWVhYU3pYuFzftujDi
fQOeXcfwU85yyTTGnCvCFknAlaXit+3ylLqi12pJOXxpA5gnDzdvjbDG0pLeOshso6bT1EAvyGoS
lYm3C+AoRzLcDCCVVz/MrmQITgTE2M6tncqNAdKwuK+J5Q==</CounterSignature></Object></Signature></ObjectCollector>